Workbook

Sheet Read me
A1: MedBrains — role test cases
A3: Why: signed in as an administrator you see every screen. These cases check what each role really sees and does.
A4: 35 roles, 568 cases. One tab per role; the Summary tab totals results.
A6: How to test
A7: 1. Take your role's username and password from the test-accounts file (shared via the password manager).
A8: 2. Sign in at app.medbrains.in with hospital code AMH.
A9: 3. Work down your role's tab. Set Result to Pass, Fail, Blocked (could not test) or leave Not run. Add your name and date.
A10: 4. For every Fail: write what you saw in Notes, take a screenshot, and report it with the case ID.
A12: Case types
A13: Sign in — the account works.
A14: Should see — every screen this role's permissions open.
A15: Must not see — screens hidden from this role, and refused even when the address is typed.
... A19: Generated from the code by scripts/generate_role_test_cases.py — regenerate after permission or menu changes.

Sheet Summary
A1: Role | B1: Login | C1: Permissions | D1: Cases | E1: Pass | F1: Fail | G1: Blocked | H1: Not run
A2: Doctor | B2: test_doctor | C2: 301 | D2: 54 | E2: =COUNTIF('Doctor'!H2:H55,"Pass") | F2: =COUNTIF('Doctor'!H2:H55,"Fail") | G2: =COUNTIF('Doctor'!H2:H55,"Blocked") | H2: =COUNTIF('Doctor'!H2:H55,"Not run")
A3: Nurse | B3: test_nurse | C3: 221 | D3: 47 | E3: =COUNTIF('Nurse'!H2:H48,"Pass") | F3: =COUNTIF('Nurse'!H2:H48,"Fail") | G3: =COUNTIF('Nurse'!H2:H48,"Blocked") | H3: =COUNTIF('Nurse'!H2:H48,"Not run")
A4: Receptionist | B4: test_receptionist | C4: 71 | D4: 31 | E4: =COUNTIF('Receptionist'!H2:H32,"Pass") | F4: =COUNTIF('Receptionist'!H2:H32,"Fail") | G4: =COUNTIF('Receptionist'!H2:H32,"Blocked") | H4: =COUNTIF('Receptionist'!H2:H32,"Not run")
A5: Lab Technician | B5: test_lab_technician | C5: 36 | D5: 16 | E5: =COUNTIF('Lab Technician'!H2:H17,"Pass") | F5: =COUNTIF('Lab Technician'!H2:H17,"Fail") | G5: =COUNTIF('Lab Technician'!H2:H17,"Blocked") | H5: =COUNTIF('Lab Technician'!H2:H17,"Not run")
A6: Pharmacist | B6: test_pharmacist | C6: 85 | D6: 24 | E6: =COUNTIF('Pharmacist'!H2:H25,"Pass") | F6: =COUNTIF('Pharmacist'!H2:H25,"Fail") | G6: =COUNTIF('Pharmacist'!H2:H25,"Blocked") | H6: =COUNTIF('Pharmacist'!H2:H25,"Not run")
A7: Billing Clerk | B7: test_billing_clerk | C7: 81 | D7: 24 | E7: =COUNTIF('Billing Clerk'!H2:H25,"Pass") | F7: =COUNTIF('Billing Clerk'!H2:H25,"Fail") | G7: =COUNTIF('Billing Clerk'!H2:H25,"Blocked") | H7: =COUNTIF('Billing Clerk'!H2:H25,"Not run")
A8: Housekeeping Staff | B8: test_housekeeping_staff | C8: 14 | D8: 12 | E8: =COUNTIF('Housekeeping Staff'!H2:H13,"Pass") | F8: =COUNTIF('Housekeeping Staff'!H2:H13,"Fail") | G8: =COUNTIF('Housekeeping Staff'!H2:H13,"Blocked") | H8: =COUNTIF('Housekeeping Staff'!H2:H13,"Not run")
A9: Facilities Manager | B9: test_facilities_manager | C9: 108 | D9: 21 | E9: =COUNTIF('Facilities Manager'!H2:H22,"Pass") | F9: =COUNTIF('Facilities Manager'!H2:H22,"Fail") | G9: =COUNTIF('Facilities Manager'!H2:H22,"Blocked") | H9: =COUNTIF('Facilities Manager'!H2:H22,"Not run")
A10: Audit Officer | B10: test_audit_officer | C10: 63 | D10: 27 | E10: =COUNTIF('Audit Officer'!H2:H28,"Pass") | F10: =COUNTIF('Audit Officer'!H2:H28,"Fail") | G10: =COUNTIF('Audit Officer'!H2:H28,"Blocked") | H10: =COUNTIF('Audit Officer'!H2:H28,"Not run")
A11: Quality Officer | B11: test_quality_officer | C11: 45 | D11: 19 | E11: =COUNTIF('Quality Officer'!H2:H20,"Pass") | F11: =COUNTIF('Quality Officer'!H2:H20,"Fail") | G11: =COUNTIF('Quality Officer'!H2:H20,"Blocked") | H11: =COUNTIF('Quality Officer'!H2:H20,"Not run")
A12: Occupational Health Officer | B12: test_occ_health_officer | C12: 12 | D12: 11 | E12: =COUNTIF('Occupational Health Officer'!H2:H12,"Pass") | F12: =COUNTIF('Occupational Health Officer'!H2:H12,"Fail") | G12: =COUNTIF('Occupational Health Officer'!H2:H12,"Blocked") | H12: =COUNTIF('Occupational Health Officer'!H2:H12,"Not run")
A13: Utilization Reviewer | B13: test_utilization_reviewer | C13: 9 | D13: 11 | E13: =COUNTIF('Utilization Reviewer'!H2:H12,"Pass") | F13: =COUNTIF('Utilization Reviewer'!H2:H12,"Fail") | G13: =COUNTIF('Utilization Reviewer'!H2:H12,"Blocked") | H13: =COUNTIF('Utilization Reviewer'!H2:H12,"Not run")
A14: Case Manager | B14: test_case_manager | C14: 10 | D14: 11 | E14: =COUNTIF('Case Manager'!H2:H12,"Pass") | F14: =COUNTIF('Case Manager'!H2:H12,"Fail") | G14: =COUNTIF('Case Manager'!H2:H12,"Blocked") | H14: =COUNTIF('Case Manager'!H2:H12,"Not run")
A15: Scheduling Admin | B15: test_scheduling_admin | C15: 12 | D15: 13 | E15: =COUNTIF('Scheduling Admin'!H2:H14,"Pass") | F15: =COUNTIF('Scheduling Admin'!H2:H14,"Fail") | G15: =COUNTIF('Scheduling Admin'!H2:H14,"Blocked") | H15: =COUNTIF('Scheduling Admin'!H2:H14,"Not run")
A16: MRD Officer | B16: test_mrd_officer | C16: 25 | D16: 16 | E16: =COUNTIF('MRD Officer'!H2:H17,"Pass") | F16: =COUNTIF('MRD Officer'!H2:H17,"Fail") | G16: =COUNTIF('MRD Officer'!H2:H17,"Blocked") | H16: =COUNTIF('MRD Officer'!H2:H17,"Not run")
A17: Canteen Staff | B17: test_canteen_staff | C17: 7 | D17: 11 | E17: =COUNTIF('Canteen Staff'!H2:H12,"Pass") | F17: =COUNTIF('Canteen Staff'!H2:H12,"Fail") | G17: =COUNTIF('Canteen Staff'!H2:H12,"Blocked") | H17: =COUNTIF('Canteen Staff'!H2:H12,"Not run")
A18: Dietitian | B18: test_dietitian | C18: 15 | D18: 11 | E18: =COUNTIF('Dietitian'!H2:H12,"Pass") | F18: =COUNTIF('Dietitian'!H2:H12,"Fail") | G18: =COUNTIF('Dietitian'!H2:H12,"Blocked") | H18: =COUNTIF('Dietitian'!H2:H12,"Not run")
A19: Security Guard | B19: test_security_guard | C19: 18 | D19: 12 | E19: =COUNTIF('Security Guard'!H2:H13,"Pass") | F19: =COUNTIF('Security Guard'!H2:H13,"Fail") | G19: =COUNTIF('Security Guard'!H2:H13,"Blocked") | H19: =COUNTIF('Security Guard'!H2:H13,"Not run")
A20: Biomedical Engineer | B20: test_biomed_engineer | C20: 31 | D20: 14 | E20: =COUNTIF('Biomedical Engineer'!H2:H15,"Pass") | F20: =COUNTIF('Biomedical Engineer'!H2:H15,"Fail") | G20: =COUNTIF('Biomedical Engineer'!H2:H15,"Blocked") | H20: =COUNTIF('Biomedical Engineer'!H2:H15,"Not run")
A21: Ambulance Driver | B21: test_ambulance_driver | C21: 12 | D21: 11 | E21: =COUNTIF('Ambulance Driver'!H2:H12,"Pass") | F21: =COUNTIF('Ambulance Driver'!H2:H12,"Fail") | G21: =COUNTIF('Ambulance Driver'!H2:H12,"Blocked") | H21: =COUNTIF('Ambulance Driver'!H2:H12,"Not run")
A22: Radiology Technician | B22: test_radiology_tech | C22: 11 | D22: 12 | E22: =COUNTIF('Radiology Technician'!H2:H13,"Pass") | F22: =COUNTIF('Radiology Technician'!H2:H13,"Fail") | G22: =COUNTIF('Radiology Technician'!H2:H13,"Blocked") | H22: =COUNTIF('Radiology Technician'!H2:H13,"Not run")
A23: CSSD Technician | B23: test_cssd_technician | C23: 13 | D23: 11 | E23: =COUNTIF('CSSD Technician'!H2:H12,"Pass") | F23: =COUNTIF('CSSD Technician'!H2:H12,"Fail") | G23: =COUNTIF('CSSD Technician'!H2:H12,"Blocked") | H23: =COUNTIF('CSSD Technician'!H2:H12,"Not run")
A24: Blood Bank Technician | B24: test_blood_bank_tech | C24: 14 | D24: 11 | E24: =COUNTIF('Blood Bank Technician'!H2:H12,"Pass") | F24: =COUNTIF('Blood Bank Technician'!H2:H12,"Fail") | G24: =COUNTIF('Blood Bank Technician'!H2:H12,"Blocked") | H24: =COUNTIF('Blood Bank Technician'!H2:H12,"Not run")
A25: Marketing Executive | B25: test_marketing_executive | C25: 13 | D25: 12 | E25: =COUNTIF('Marketing Executive'!H2:H13,"Pass") | F25: =COUNTIF('Marketing Executive'!H2:H13,"Fail") | G25: =COUNTIF('Marketing Executive'!H2:H13,"Blocked") | H25: =COUNTIF('Marketing Executive'!H2:H13,"Not run")
A26: Front Office Staff | B26: test_front_office_staff | C26: 46 | D26: 17 | E26: =COUNTIF('Front Office Staff'!H2:H18,"Pass") | F26: =COUNTIF('Front Office Staff'!H2:H18,"Fail") | G26: =COUNTIF('Front Office Staff'!H2:H18,"Blocked") | H26: =COUNTIF('Front Office Staff'!H2:H18,"Not run")
A27: Infection Control Officer | B27: test_infection_control_officer | C27: 16 | D27: 11 | E27: =COUNTIF('Infection Control Officer'!H2:H12,"Pass") | F27: =COUNTIF('Infection Control Officer'!H2:H12,"Fail") | G27: =COUNTIF('Infection Control Officer'!H2:H12,"Blocked") | H27: =COUNTIF('Infection Control Officer'!H2:H12,"Not run")
A28: Procurement Officer | B28: test_procurement_officer | C28: 16 | D28: 12 | E28: =COUNTIF('Procurement Officer'!H2:H13,"Pass") | F28: =COUNTIF('Procurement Officer'!H2:H13,"Fail") | G28: =COUNTIF('Procurement Officer'!H2:H13,"Blocked") | H28: =COUNTIF('Procurement Officer'!H2:H13,"Not run")
A29: Store Keeper | B29: test_store_keeper | C29: 25 | D29: 12 | E29: =COUNTIF('Store Keeper'!H2:H13,"Pass") | F29: =COUNTIF('Store Keeper'!H2:H13,"Fail") | G29: =COUNTIF('Store Keeper'!H2:H13,"Blocked") | H29: =COUNTIF('Store Keeper'!H2:H13,"Not run")
A30: HR Officer | B30: test_hr_officer | C30: 17 | D30: 12 | E30: =COUNTIF('HR Officer'!H2:H13,"Pass") | F30: =COUNTIF('HR Officer'!H2:H13,"Fail") | G30: =COUNTIF('HR Officer'!H2:H13,"Blocked") | H30: =COUNTIF('HR Officer'!H2:H13,"Not run")
A31: Camp Coordinator | B31: test_camp_coordinator | C31: 25 | D31: 12 | E31: =COUNTIF('Camp Coordinator'!H2:H13,"Pass") | F31: =COUNTIF('Camp Coordinator'!H2:H13,"Fail") | G31: =COUNTIF('Camp Coordinator'!H2:H13,"Blocked") | H31: =COUNTIF('Camp Coordinator'!H2:H13,"Not run")
A32: Insurance Officer | B32: test_insurance_officer | C32: 11 | D32: 11 | E32: =COUNTIF('Insurance Officer'!H2:H12,"Pass") | F32: =COUNTIF('Insurance Officer'!H2:H12,"Fail") | G32: =COUNTIF('Insurance Officer'!H2:H12,"Blocked") | H32: =COUNTIF('Insurance Officer'!H2:H12,"Not run")
A33: Wall Display | B33: test_display_device | C33: 1 | D33: 8 | E33: =COUNTIF('Wall Display'!H2:H9,"Pass") | F33: =COUNTIF('Wall Display'!H2:H9,"Fail") | G33: =COUNTIF('Wall Display'!H2:H9,"Blocked") | H33: =COUNTIF('Wall Display'!H2:H9,"Not run")
A34: OT Staff | B34: test_ot_staff | C34: 20 | D34: 11 | E34: =COUNTIF('OT Staff'!H2:H12,"Pass") | F34: =COUNTIF('OT Staff'!H2:H12,"Fail") | G34: =COUNTIF('OT Staff'!H2:H12,"Blocked") | H34: =COUNTIF('OT Staff'!H2:H12,"Not run")
A35: Delivery runner | B35: test_delivery_runner | C35: 4 | D35: 11 | E35: =COUNTIF('Delivery runner'!H2:H12,"Pass") | F35: =COUNTIF('Delivery runner'!H2:H12,"Fail") | G35: =COUNTIF('Delivery runner'!H2:H12,"Blocked") | H35: =COUNTIF('Delivery runner'!H2:H12,"Not run")
A36: Staff (awaiting role) | B36: test_staff | C36: 2 | D36: 9 | E36: =COUNTIF('Staff (awaiting role)'!H2:H10,"Pass") | F36: =COUNTIF('Staff (awaiting role)'!H2:H10,"Fail") | G36: =COUNTIF('Staff (awaiting role)'!H2:H10,"Blocked") | H36: =COUNTIF('Staff (awaiting role)'!H2:H10,"Not run")

Sheet Doctor
A1: Case | B1: Type | C1: Area | D1: What to test | E1: Steps | F1: Expected | G1: Permission | H1: Result | I1: Tester | J1: Date | K1: Notes
A2: doctor:sign-in | B2: Sign in | C2: Sign in | D2: Sign in as Doctor | E2: app.medbrains.in → hospital code AMH → username test_doctor and the password from your test-accounts file. | F2: You are signed in; the header shows 'TEST - Doctor'; you land on a page you can use (not an error). | H2: Not run
A3: doctor:see:/dashboard | B3: Should see | C3: Core | D3: Open Dashboard | E3: Menu → Core → Dashboard (/dashboard) | F3: The screen opens with no 'access denied' or error message. Lists load; an empty list says so. Buttons to add or change things appear only where this role should do that. | G3: dashboard.view | H3: Not run
A4: doctor:see:/approvals | B4: Should see | C4: Core | D4: Open Approvals | E4: Menu → Core → Approvals (/approvals) | F4: The screen opens with no 'access denied' or error message. Lists load; an empty list says so. Buttons to add or change things appear only where this role should do that. | H4: Not run
A5: doctor:see:/health-pulse | B5: Should see | C5: Core | D5: Open Health Pulse | E5: Menu → Core → Health Pulse (/health-pulse) | F5: The screen opens with no 'access denied' or error message. Lists load; an empty list says so. Buttons to add or change things appear only where this role should do that. | G5: dashboard.view | H5: Not run
A6: doctor:see:/patients | B6: Should see | C6: Clinical | D6: Open Patients | E6: Menu → Clinical → Patients (/patients) | F6: The screen opens with no 'access denied' or error message. Lists load; an empty list says so. Buttons to add or change things appear only where this role should do that. | G6: patients.list | H6: Not run
A7: doctor:see:/opd | B7: Should see | C7: Clinical | D7: Open OPD Queue | E7: Menu → Clinical → OPD Queue (/opd) | F7: The screen opens with no 'access denied' or error message. Lists load; an empty list says so. Buttons to add or change things appear only where this role should do that. | G7: opd.queue.list | H7: Not run
A8: doctor:see:/telemedicine | B8: Should see | C8: Clinical | D8: Open Telemedicine | E8: Menu → Clinical → Telemedicine (/telemedicine) | F8: The screen opens with no 'access denied' or error message. Lists load; an empty list says so. Buttons to add or change things appear only where this role should do that. | G8: opd.queue.view | H8: Not run
A9: doctor:see:/doctor/signoffs | B9: Should see | C9: Clinical | D9: Open Doctor Sign-offs | E9: Menu → Clinical → Doctor Sign-offs (/doctor/signoffs) | F9: The screen opens with no 'access denied' or error message. Lists load; an empty list says so. Buttons to add or change things appear only where this role should do that. | G9: doctor.signoffs.view_own | H9: Not run
A10: doctor:see:/emergency | B10: Should see | C10: Clinical | D10: Open Emergency | E10: Menu → Clinical → Emergency (/emergency) | F10: The screen opens with no 'access denied' or error message. Lists load; an empty list says so. Buttons to add or change things appear only where this role should do that. | G10: emergency.visits.list | H10: Not run
A11: doctor:see:/order-sets | B11: Should see | C11: Clinical | D11: Open Order Sets | E11: Menu → Clinical → Order Sets (/order-sets) | F11: The screen opens with no 'access denied' or error message. Lists load; an empty list says so. Buttons to add or change things appear only where this role should do that. | G11: order_sets.templates.list | H11: Not run
A12: doctor:see:/chronic-care | B12: Should see | C12: Clinical | D12: Open Chronic Care | E12: Menu → Clinical → Chronic Care (/chronic-care) | F12: The screen opens with no 'access denied' or error message. Lists load; an empty list says so. Buttons to add or change things appear only where this role should do that. | G12: chronic.enrollments.list | H12: Not run
A13: doctor:see:/home-healthcare | B13: Should see | C13: Clinical | D13: Open Home healthcare | E13: Menu → Clinical → Home healthcare (/home-healthcare) | F13: The screen opens with no 'access denied' or error message. Lists load; an empty list says so. Buttons to add or change things appear only where this role should do that. | G13: home_health.list | H13: Not run
A14: doctor:see:/home-visits | B14: Should see | C14: Clinical | D14: Open Home visits | E14: Menu → Clinical → Home visits (/home-visits) | F14: The screen opens with no 'access denied' or error message. Lists load; an empty list says so. Buttons to add or change things appear only where this role should do that. | G14: home_health.list | H14: Not run
A15: doctor:see:/lab | B15: Should see | C15: Diagnostics | D15: Open Lab | E15: Menu → Diagnostics → Lab (/lab) | F15: The screen opens with no 'access denied' or error message. Lists load; an empty list says so. Buttons to add or change things appear only where this role should do that. (Hidden if the hospital has this module switched off.) | G15: lab.orders.list | H15: Not run
A16: doctor:see:/pharmacy | B16: Should see | C16: Diagnostics | D16: Open Pharmacy | E16: Menu → Diagnostics → Pharmacy (/pharmacy) | F16: The screen opens with no 'access denied' or error message. Lists load; an empty list says so. Buttons to add or change things appear only where this role should do that. | G16: pharmacy.prescriptions.list | H16: Not run
... A45: doctor:see:/admin/documents | B45: Should see | C45: Administration | D45: Open Documents & Printing | E45: Menu → Administration → Admin → Documents & Printing (/admin/documents) | F45: The screen opens with no 'access denied' or error message. Lists load; an empty list says so. Buttons to add or change things appear only where this role should do that. | G45: documents.templates.list | H45: Not run
A46: doctor:menu | B46: Must not see | C46: Menu | D46: Menu shows only this role's screens | E46: Look through every menu group. | F46: These must NOT be in the menu: Token Board, Token Console, Appointments, Radiology, Ward Stock, Pharmacy Finance, Fulfilment Queue, Home Deliveries, Collection Counter, Blood Bank, Nurse Activities, Diet & Kitchen, Billing, Procurement, Payroll, Smart Scheduling, Command Center, Communications, Camp Management, Ambulance, Housekeeping, CSSD, Facilities Management, Biomedical Engineering, Security, HR & Staffing, Clinical Knowledge, Directory, Hospital groups, Marketing, Health packages, Testimonials, Micro-site settings, Quality, Infection Control, Analytics & Dashboards, Audit Trail, Utilization Review, Case Management, Long-term care, Occupational Health, Users, Doctors, Roles & Permissions, Access Groups, Single Sign-On, Access Requests, NABH Indicators, Setup Center, Onboarding workbook, Settings, Document Templates, Built-in Pipelines, Forms, Test cycles, API keys, Webhooks, Retrospective Entry, Device Integration, Paired Devices, Queues, Message Simulator. | H46: Not run
A47: doctor:url:/admin/users | B47: Must not see | C47: Administration | D47: Typing the address of Users | E47: Type app.medbrains.in/admin/users into the address bar. | F47: You get an 'access denied' page or are sent back — none of that screen's data is shown, even briefly. | G47: admin.users.list | H47: Not run
A48: doctor:url:/audit | B48: Must not see | C48: Compliance | D48: Typing the address of Audit Trail | E48: Type app.medbrains.in/audit into the address bar. | F48: You get an 'access denied' page or are sent back — none of that screen's data is shown, even briefly. | G48: audit.log.view | H48: Not run
A49: doctor:url:/billing | B49: Must not see | C49: Finance | D49: Typing the address of Billing | E49: Type app.medbrains.in/billing into the address bar. | F49: You get an 'access denied' page or are sent back — none of that screen's data is shown, even briefly. | G49: billing.invoices.list | H49: Not run
A50: doctor:url:/hr/payroll | B50: Must not see | C50: Finance | D50: Typing the address of Payroll | E50: Type app.medbrains.in/hr/payroll into the address bar. | F50: You get an 'access denied' page or are sent back — none of that screen's data is shown, even briefly. | G50: hr.payroll.structures.list | H50: Not run
A51: doctor:wf:consult-a-patient-end-to-end | B51: Workflow | C51: OPD Queue | D51: Consult a patient end to end | E51: OPD Queue → call your next patient → Start → record complaint, examination, diagnosis (ICD-10 search), advice → prescribe two medicines → Complete. | F51: The visit is completed; the case sheet shows the note signed by you; the consultation is on the patient's bill at your fee. | H51: Not run
A52: doctor:wf:free-revisit-inside-the-window | B52: Workflow | C52: OPD Queue | D52: Free revisit inside the window | E52: (Billing settings has a free revisit window, e.g. 7 days.) Consult the same patient again within the window. | F52: The second consultation is billed ₹0, marked 'Free revisit (day N of M)'. | H52: Not run
A53: doctor:wf:order-a-lab-test-and-an-x-ray | B53: Workflow | C53: Orders | D53: Order a lab test and an X-ray | E53: In a visit, order a CBC and a chest X-ray. | F53: The CBC appears in Lab and the X-ray in Radiology as ordered for this patient. | H53: Not run
A54: doctor:wf:spectacle-prescription | B54: Workflow | C54: Ophthalmology | D54: Spectacle prescription | E54: In a visit: Specialty tab → Ophthalmology → New exam. Enter vision, sphere/cylinder/axis for both eyes, lens type. Sign prescription (it should ask for the pupillary distance first) → PDF → Spectacle prescription. | F54: Signing is refused until PD is entered; once signed the exam is read-only; the PDF shows your name and registration number, not DRAFT. | H54: Not run
A55: doctor:wf:clear-pending-sign-offs | B55: Workflow | C55: Doctor Sign-offs | D55: Clear pending sign-offs | E55: Doctor Sign-offs → open an unsigned note → sign. | F55: It leaves the pending list and shows as signed on the case sheet. | H55: Not run

Sheet Nurse
A1: Case | B1: Type | C1: Area | D1: What to test | E1: Steps | F1: Expected | G1: Permission | H1: Result | I1: Tester | J1: Date | K1: Notes
A2: nurse:sign-in | B2: Sign in | C2: Sign in | D2: Sign in as Nurse | E2: app.medbrains.in → hospital code AMH → username test_nurse and the password from your test-accounts file. | F2: You are signed in; the header shows 'TEST - Nurse'; you land on a page you can use (not an error). | H2: Not run
A3: nurse:see:/dashboard | B3: Should see | C3: Core | D3: Open Dashboard | E3: Menu → Core → Dashboard (/dashboard) | F3: The screen opens with no 'access denied' or error message. Lists load; an empty list says so. Buttons to add or change things appear only where this role should do that. | G3: dashboard.view | H3: Not run
A4: nurse:see:/approvals | B4: Should see | C4: Core | D4: Open Approvals | E4: Menu → Core → Approvals (/approvals) | F4: The screen opens with no 'access denied' or error message. Lists load; an empty list says so. Buttons to add or change things appear only where this role should do that. | H4: Not run
A5: nurse:see:/health-pulse | B5: Should see | C5: Core | D5: Open Health Pulse | E5: Menu → Core → Health Pulse (/health-pulse) | F5: The screen opens with no 'access denied' or error message. Lists load; an empty list says so. Buttons to add or change things appear only where this role should do that. | G5: dashboard.view | H5: Not run
A6: nurse:see:/patients | B6: Should see | C6: Clinical | D6: Open Patients | E6: Menu → Clinical → Patients (/patients) | F6: The screen opens with no 'access denied' or error message. Lists load; an empty list says so. Buttons to add or change things appear only where this role should do that. | G6: patients.list | H6: Not run
A7: nurse:see:/opd | B7: Should see | C7: Clinical | D7: Open OPD Queue | E7: Menu → Clinical → OPD Queue (/opd) | F7: The screen opens with no 'access denied' or error message. Lists load; an empty list says so. Buttons to add or change things appear only where this role should do that. | G7: opd.queue.list | H7: Not run
A8: nurse:see:/telemedicine | B8: Should see | C8: Clinical | D8: Open Telemedicine | E8: Menu → Clinical → Telemedicine (/telemedicine) | F8: The screen opens with no 'access denied' or error message. Lists load; an empty list says so. Buttons to add or change things appear only where this role should do that. | G8: opd.queue.view | H8: Not run
A9: nurse:see:/emergency | B9: Should see | C9: Clinical | D9: Open Emergency | E9: Menu → Clinical → Emergency (/emergency) | F9: The screen opens with no 'access denied' or error message. Lists load; an empty list says so. Buttons to add or change things appear only where this role should do that. | G9: emergency.visits.list | H9: Not run
A10: nurse:see:/chronic-care | B10: Should see | C10: Clinical | D10: Open Chronic Care | E10: Menu → Clinical → Chronic Care (/chronic-care) | F10: The screen opens with no 'access denied' or error message. Lists load; an empty list says so. Buttons to add or change things appear only where this role should do that. | G10: chronic.enrollments.list | H10: Not run
A11: nurse:see:/home-healthcare | B11: Should see | C11: Clinical | D11: Open Home healthcare | E11: Menu → Clinical → Home healthcare (/home-healthcare) | F11: The screen opens with no 'access denied' or error message. Lists load; an empty list says so. Buttons to add or change things appear only where this role should do that. | G11: home_health.list | H11: Not run
A12: nurse:see:/home-visits | B12: Should see | C12: Clinical | D12: Open Home visits | E12: Menu → Clinical → Home visits (/home-visits) | F12: The screen opens with no 'access denied' or error message. Lists load; an empty list says so. Buttons to add or change things appear only where this role should do that. | G12: home_health.list | H12: Not run
A13: nurse:see:/lab | B13: Should see | C13: Diagnostics | D13: Open Lab | E13: Menu → Diagnostics → Lab (/lab) | F13: The screen opens with no 'access denied' or error message. Lists load; an empty list says so. Buttons to add or change things appear only where this role should do that. (Hidden if the hospital has this module switched off.) | G13: lab.orders.list | H13: Not run
A14: nurse:see:/radiology | B14: Should see | C14: Diagnostics | D14: Open Radiology | E14: Menu → Diagnostics → Radiology (/radiology) | F14: The screen opens with no 'access denied' or error message. Lists load; an empty list says so. Buttons to add or change things appear only where this role should do that. (Hidden if the hospital has this module switched off.) | G14: radiology.orders.list | H14: Not run
A15: nurse:see:/pharmacy | B15: Should see | C15: Diagnostics | D15: Open Pharmacy | E15: Menu → Diagnostics → Pharmacy (/pharmacy) | F15: The screen opens with no 'access denied' or error message. Lists load; an empty list says so. Buttons to add or change things appear only where this role should do that. | G15: pharmacy.prescriptions.list | H15: Not run
A16: nurse:see:/ipd | B16: Should see | C16: Inpatient | D16: Open IPD | E16: Menu → Inpatient → IPD (/ipd) | F16: The screen opens with no 'access denied' or error message. Lists load; an empty list says so. Buttons to add or change things appear only where this role should do that. | G16: ipd.admissions.list | H16: Not run
... A39: nurse:see:/admin/documents | B39: Should see | C39: Administration | D39: Open Documents & Printing | E39: Menu → Administration → Admin → Documents & Printing (/admin/documents) | F39: The screen opens with no 'access denied' or error message. Lists load; an empty list says so. Buttons to add or change things appear only where this role should do that. | G39: documents.templates.list | H39: Not run
A40: nurse:menu | B40: Must not see | C40: Menu | D40: Menu shows only this role's screens | E40: Look through every menu group. | F40: These must NOT be in the menu: Token Board, Token Console, Appointments, Doctor Sign-offs, Order Sets, Ward Stock, Pharmacy Finance, Fulfilment Queue, Home Deliveries, Collection Counter, Blood Bank, Case sheet review, Operation Theatre, Diet & Kitchen, Billing, Insurance & TPA, Procurement, Payroll, Smart Scheduling, Command Center, Communications, Camp Management, Ambulance, Housekeeping, CSSD, Facilities Management, Biomedical Engineering, Security, HR & Staffing, Medical Records, Clinical Knowledge, Directory, Hospital groups, Marketing, Health packages, Testimonials, Micro-site settings, Quality, Infection Control, Consent Management, Analytics & Dashboards, Audit Trail, Utilization Review, Case Management, Clinical trials, Occupational Health, Users, Doctors, Roles & Permissions, Access Groups, Single Sign-On, Access Requests, NABH Indicators, Setup Center, Onboarding workbook, Settings, Document Templates, Built-in Pipelines, Forms, Test cycles, API keys, Webhooks, Doctor Schedules, Retrospective Entry, Device Integration, Paired Devices, Queues, Message Simulator. | H40: Not run
A41: nurse:url:/admin/users | B41: Must not see | C41: Administration | D41: Typing the address of Users | E41: Type app.medbrains.in/admin/users into the address bar. | F41: You get an 'access denied' page or are sent back — none of that screen's data is shown, even briefly. | G41: admin.users.list | H41: Not run
A42: nurse:url:/audit | B42: Must not see | C42: Compliance | D42: Typing the address of Audit Trail | E42: Type app.medbrains.in/audit into the address bar. | F42: You get an 'access denied' page or are sent back — none of that screen's data is shown, even briefly. | G42: audit.log.view | H42: Not run
A43: nurse:url:/billing | B43: Must not see | C43: Finance | D43: Typing the address of Billing | E43: Type app.medbrains.in/billing into the address bar. | F43: You get an 'access denied' page or are sent back — none of that screen's data is shown, even briefly. | G43: billing.invoices.list | H43: Not run
A44: nurse:url:/mrd | B44: Must not see | C44: Operations | D44: Typing the address of Medical Records | E44: Type app.medbrains.in/mrd into the address bar. | F44: You get an 'access denied' page or are sent back — none of that screen's data is shown, even briefly. | H44: Not run
A45: nurse:wf:record-vitals-before-the-doctor | B45: Workflow | C45: OPD Queue | D45: Record vitals before the doctor | E45: OPD Queue → a waiting patient → Vitals → enter BP, pulse, temperature, SpO2, weight. | F45: Vitals save; the doctor sees them on the visit; an out-of-range value is flagged. | H45: Not run
A46: nurse:wf:print-a-wristband-for-an-admitted-patient | B46: Workflow | C46: IPD | D46: Print a wristband for an admitted patient | E46: IPD → open an admission → Wristband → Send to print queue (or Generate & open PDF). | F46: With a wristband printer set up: 'Queued on <printer>' and the band prints with name, UHID and barcode. Without one: a clear 'no printer' message — never silence. | H46: Not run
A47: nurse:wf:give-a-scheduled-medicine-emar | B47: Workflow | C47: Nurse Activities | D47: Give a scheduled medicine (eMAR) | E47: Nurse Activities → medication round → scan or pick the patient → give a due dose. | F47: The dose is recorded with time and your name; giving it twice is warned. | H47: Not run
A48: nurse:wf:record-an-eye-workup-but-cannot-sign-it | B48: Workflow | C48: Ophthalmology | D48: Record an eye workup but cannot sign it | E48: Ophthalmology → New exam → enter vision and refraction → Save. | F48: Saved as a draft. There is NO 'Sign prescription' button for a nurse. | H48: Not run

Sheet Receptionist
A1: Case | B1: Type | C1: Area | D1: What to test | E1: Steps | F1: Expected | G1: Permission | H1: Result | I1: Tester | J1: Date | K1: Notes
A2: receptionist:sign-in | B2: Sign in | C2: Sign in | D2: Sign in as Receptionist | E2: app.medbrains.in → hospital code AMH → username test_receptionist and the password from your test-accounts file. | F2: You are signed in; the header shows 'TEST - Receptionist'; you land on a page you can use (not an error). | H2: Not run
A3: receptionist:see:/dashboard | B3: Should see | C3: Core | D3: Open Dashboard | E3: Menu → Core → Dashboard (/dashboard) | F3: The screen opens with no 'access denied' or error message. Lists load; an empty list says so. Buttons to add or change things appear only where this role should do that. | G3: dashboard.view | H3: Not run
A4: receptionist:see:/approvals | B4: Should see | C4: Core | D4: Open Approvals | E4: Menu → Core → Approvals (/approvals) | F4: The screen opens with no 'access denied' or error message. Lists load; an empty list says so. Buttons to add or change things appear only where this role should do that. | H4: Not run
A5: receptionist:see:/health-pulse | B5: Should see | C5: Core | D5: Open Health Pulse | E5: Menu → Core → Health Pulse (/health-pulse) | F5: The screen opens with no 'access denied' or error message. Lists load; an empty list says so. Buttons to add or change things appear only where this role should do that. | G5: dashboard.view | H5: Not run
A6: receptionist:see:/token-board | B6: Should see | C6: Core | D6: Open Token Board | E6: Menu → Core → Token Board (/token-board) | F6: The screen opens with no 'access denied' or error message. Lists load; an empty list says so. Buttons to add or change things appear only where this role should do that. | G6: front_office.queue.list | H6: Not run
A7: receptionist:see:/token-console | B7: Should see | C7: Core | D7: Open Token Console | E7: Menu → Core → Token Console (/token-console) | F7: The screen opens with no 'access denied' or error message. Lists load; an empty list says so. Buttons to add or change things appear only where this role should do that. | G7: front_office.queue.manage | H7: Not run
A8: receptionist:see:/patients | B8: Should see | C8: Clinical | D8: Open Patients | E8: Menu → Clinical → Patients (/patients) | F8: The screen opens with no 'access denied' or error message. Lists load; an empty list says so. Buttons to add or change things appear only where this role should do that. | G8: patients.list | H8: Not run
A9: receptionist:see:/opd | B9: Should see | C9: Clinical | D9: Open OPD Queue | E9: Menu → Clinical → OPD Queue (/opd) | F9: The screen opens with no 'access denied' or error message. Lists load; an empty list says so. Buttons to add or change things appear only where this role should do that. | G9: opd.queue.list | H9: Not run
A10: receptionist:see:/opd/appointments | B10: Should see | C10: Clinical | D10: Open Appointments | E10: Menu → Clinical → Appointments (/opd/appointments) | F10: The screen opens with no 'access denied' or error message. Lists load; an empty list says so. Buttons to add or change things appear only where this role should do that. | G10: opd.appointment.list | H10: Not run
A11: receptionist:see:/telemedicine | B11: Should see | C11: Clinical | D11: Open Telemedicine | E11: Menu → Clinical → Telemedicine (/telemedicine) | F11: The screen opens with no 'access denied' or error message. Lists load; an empty list says so. Buttons to add or change things appear only where this role should do that. | G11: opd.queue.view | H11: Not run
A12: receptionist:see:/emergency | B12: Should see | C12: Clinical | D12: Open Emergency | E12: Menu → Clinical → Emergency (/emergency) | F12: The screen opens with no 'access denied' or error message. Lists load; an empty list says so. Buttons to add or change things appear only where this role should do that. | G12: emergency.visits.list | H12: Not run
A13: receptionist:see:/billing | B13: Should see | C13: Finance | D13: Open Billing | E13: Menu → Finance → Billing (/billing) | F13: The screen opens with no 'access denied' or error message. Lists load; an empty list says so. Buttons to add or change things appear only where this role should do that. | G13: billing.invoices.list | H13: Not run
A14: receptionist:see:/insurance | B14: Should see | C14: Finance | D14: Open Insurance & TPA | E14: Menu → Finance → Insurance & TPA (/insurance) | F14: The screen opens with no 'access denied' or error message. Lists load; an empty list says so. Buttons to add or change things appear only where this role should do that. | G14: insurance.verification.list | H14: Not run
A15: receptionist:see:/front-office | B15: Should see | C15: Operations | D15: Open Front Office | E15: Menu → Operations → Front Office (/front-office) | F15: The screen opens with no 'access denied' or error message. Lists load; an empty list says so. Buttons to add or change things appear only where this role should do that. | G15: front_office.visitors.list, front_office.visitors.create, front_office.visitors.manage… | H15: Not run
A16: receptionist:see:/camp | B16: Should see | C16: Operations | D16: Open Camp Management | E16: Menu → Operations → Camp Management (/camp) | F16: The screen opens with no 'access denied' or error message. Lists load; an empty list says so. Buttons to add or change things appear only where this role should do that. | G16: camp.list | H16: Not run
... A23: receptionist:see:/admin/queues | B23: Should see | C23: Administration | D23: Open Queues | E23: Menu → Administration → Admin → Queues (/admin/queues) | F23: The screen opens with no 'access denied' or error message. Lists load; an empty list says so. Buttons to add or change things appear only where this role should do that. | G23: front_office.queue.config.view | H23: Not run
A24: receptionist:menu | B24: Must not see | C24: Menu | D24: Menu shows only this role's screens | E24: Look through every menu group. | F24: These must NOT be in the menu: Doctor Sign-offs, Order Sets, Chronic Care, Home healthcare, Home visits, Lab, Radiology, Ward Stock, Pharmacy, Pharmacy Finance, Fulfilment Queue, Home Deliveries, Collection Counter, Blood Bank, IPD, Care View, Case sheet review, ICU, Nurse Activities, Operation Theatre, Diet & Kitchen, Bedside Portal, Procurement, Indent & Store, Materials, Payroll, Smart Scheduling, Command Center, Communications, Ambulance, Housekeeping, CSSD, Facilities Management, Biomedical Engineering, Security, HR & Staffing, Medical Records, Clinical Knowledge, Directory, Hospital groups, Inter-hospital transfers, Inter-hospital stock, Quality, Infection Control, Consent Management, Regulatory Compliance, Analytics & Dashboards, Reports Center, Audit Trail, Utilization Review, Case Management, Ophthalmology, Dental, Cath Lab, Endoscopy, Psychiatry, Physical Medicine, Palliative Care, Maternity, Other Specialties, Clinical trials, Long-term care, Occupational Health, Users, Doctors, Roles & Permissions, Access Groups, Single Sign-On, Access Requests, NABH Indicators, Setup Center, Onboarding workbook, Settings, Document Templates, Built-in Pipelines, Forms, Test cycles, API keys, Webhooks, Doctor Schedules, Retrospective Entry, Device Integration, Paired Devices, Message Simulator. | H24: Not run
A25: receptionist:url:/admin/users | B25: Must not see | C25: Administration | D25: Typing the address of Users | E25: Type app.medbrains.in/admin/users into the address bar. | F25: You get an 'access denied' page or are sent back — none of that screen's data is shown, even briefly. | G25: admin.users.list | H25: Not run
A26: receptionist:url:/audit | B26: Must not see | C26: Compliance | D26: Typing the address of Audit Trail | E26: Type app.medbrains.in/audit into the address bar. | F26: You get an 'access denied' page or are sent back — none of that screen's data is shown, even briefly. | G26: audit.log.view | H26: Not run
A27: receptionist:url:/mrd | B27: Must not see | C27: Operations | D27: Typing the address of Medical Records | E27: Type app.medbrains.in/mrd into the address bar. | F27: You get an 'access denied' page or are sent back — none of that screen's data is shown, even briefly. | H27: Not run
A28: receptionist:url:/pharmacy | B28: Must not see | C28: Diagnostics | D28: Typing the address of Pharmacy | E28: Type app.medbrains.in/pharmacy into the address bar. | F28: You get an 'access denied' page or are sent back — none of that screen's data is shown, even briefly. | G28: pharmacy.prescriptions.list | H28: Not run
A29: receptionist:wf:register-a-new-patient | B29: Workflow | C29: Patients | D29: Register a new patient | E29: Patients → Register. Enter name, sex, date of birth, phone, address. Save. | F29: A UHID is issued and shown. Searching the name or phone in Patients finds them. | H29: Not run
A30: receptionist:wf:duplicate-check-on-registration | B30: Workflow | C30: Patients | D30: Duplicate check on registration | E30: Register the same name + phone + date of birth again. | F30: The system warns of a possible duplicate before saving a second record. | H30: Not run
A31: receptionist:wf:start-an-opd-visit-with-a-token | B31: Workflow | C31: OPD Queue | D31: Start an OPD visit with a token | E31: OPD Queue → new visit for the patient registered above. Pick a department and doctor. | F31: A token number is issued; the patient appears in the OPD queue as waiting; a token slip can be printed. | H31: Not run
A32: receptionist:wf:book-and-check-in-an-appointment | B32: Workflow | C32: Appointments | D32: Book and check in an appointment | E32: Appointments → book a slot with a doctor for tomorrow; then for today, and check the patient in. | F32: The slot shows as booked; on check-in the patient joins that doctor's queue. | H32: Not run

Sheet Lab Technician
A1: Case | B1: Type | C1: Area | D1: What to test | E1: Steps | F1: Expected | G1: Permission | H1: Result | I1: Tester | J1: Date | K1: Notes
A2: lab_technician:sign-in | B2: Sign in | C2: Sign in | D2: Sign in as Lab Technician | E2: app.medbrains.in → hospital code AMH → username test_lab_technician and the password from your test-accounts file. | F2: You are signed in; the header shows 'TEST - Lab Technician'; you land on a page you can use (not an error). | H2: Not run
A3: lab_technician:see:/dashboard | B3: Should see | C3: Core | D3: Open Dashboard | E3: Menu → Core → Dashboard (/dashboard) | F3: The screen opens with no 'access denied' or error message. Lists load; an empty list says so. Buttons to add or change things appear only where this role should do that. | G3: dashboard.view | H3: Not run
A4: lab_technician:see:/approvals | B4: Should see | C4: Core | D4: Open Approvals | E4: Menu → Core → Approvals (/approvals) | F4: The screen opens with no 'access denied' or error message. Lists load; an empty list says so. Buttons to add or change things appear only where this role should do that. | H4: Not run
A5: lab_technician:see:/health-pulse | B5: Should see | C5: Core | D5: Open Health Pulse | E5: Menu → Core → Health Pulse (/health-pulse) | F5: The screen opens with no 'access denied' or error message. Lists load; an empty list says so. Buttons to add or change things appear only where this role should do that. | G5: dashboard.view | H5: Not run
A6: lab_technician:see:/lab | B6: Should see | C6: Diagnostics | D6: Open Lab | E6: Menu → Diagnostics → Lab (/lab) | F6: The screen opens with no 'access denied' or error message. Lists load; an empty list says so. Buttons to add or change things appear only where this role should do that. (Hidden if the hospital has this module switched off.) | G6: lab.orders.list | H6: Not run
A7: lab_technician:see:/front-office | B7: Should see | C7: Operations | D7: Open Front Office | E7: Menu → Operations → Front Office (/front-office) | F7: The screen opens with no 'access denied' or error message. Lists load; an empty list says so. Buttons to add or change things appear only where this role should do that. | G7: front_office.visitors.list, front_office.visitors.create, front_office.visitors.manage… | H7: Not run
A8: lab_technician:see:/lms | B8: Should see | C8: Operations | D8: Open Learning (LMS) | E8: Menu → Operations → Learning (LMS) (/lms) | F8: The screen opens with no 'access denied' or error message. Lists load; an empty list says so. Buttons to add or change things appear only where this role should do that. | G8: lms.my_learning.view | H8: Not run
A9: lab_technician:see:/reports | B9: Should see | C9: Compliance | D9: Open Reports Center | E9: Menu → Compliance → Reports Center (/reports) | F9: The screen opens with no 'access denied' or error message. Lists load; an empty list says so. Buttons to add or change things appear only where this role should do that. | G9: analytics.view, billing.reports.view, quality.indicators.list… | H9: Not run
A10: lab_technician:see:/admin/documents | B10: Should see | C10: Administration | D10: Open Documents & Printing | E10: Menu → Administration → Admin → Documents & Printing (/admin/documents) | F10: The screen opens with no 'access denied' or error message. Lists load; an empty list says so. Buttons to add or change things appear only where this role should do that. | G10: documents.templates.list | H10: Not run
A11: lab_technician:menu | B11: Must not see | C11: Menu | D11: Menu shows only this role's screens | E11: Look through every menu group. | F11: These must NOT be in the menu: Token Board, Token Console, Patients, OPD Queue, Appointments, Telemedicine, Doctor Sign-offs, Emergency, Order Sets, Chronic Care, Home healthcare, Home visits, Radiology, Ward Stock, Pharmacy, Pharmacy Finance, Fulfilment Queue, Home Deliveries, Collection Counter, Blood Bank, IPD, Care View, Case sheet review, ICU, Nurse Activities, Operation Theatre, Diet & Kitchen, Bedside Portal, Billing, Insurance & TPA, Procurement, Indent & Store, Materials, Payroll, Smart Scheduling, Command Center, Communications, Camp Management, Ambulance, Housekeeping, CSSD, Facilities Management, Biomedical Engineering, Security, HR & Staffing, Medical Records, Clinical Knowledge, Directory, Hospital groups, Inter-hospital transfers, Inter-hospital stock, Marketing, Health packages, Testimonials, Micro-site settings, Quality, Infection Control, Consent Management, Regulatory Compliance, Analytics & Dashboards, Audit Trail, Utilization Review, Case Management, Ophthalmology, Dental, Cath Lab, Endoscopy, Psychiatry, Physical Medicine, Palliative Care, Maternity, Other Specialties, Clinical trials, Long-term care, Occupational Health, Users, Doctors, Roles & Permissions, Access Groups, Single Sign-On, Access Requests, NABH Indicators, Setup Center, Onboarding workbook, Settings, Document Templates, Built-in Pipelines, Forms, Test cycles, API keys, Webhooks, Doctor Schedules, Retrospective Entry, Device Integration, Paired Devices, Queues, Message Simulator. | H11: Not run
A12: lab_technician:url:/admin/users | B12: Must not see | C12: Administration | D12: Typing the address of Users | E12: Type app.medbrains.in/admin/users into the address bar. | F12: You get an 'access denied' page or are sent back — none of that screen's data is shown, even briefly. | G12: admin.users.list | H12: Not run
A13: lab_technician:url:/audit | B13: Must not see | C13: Compliance | D13: Typing the address of Audit Trail | E13: Type app.medbrains.in/audit into the address bar. | F13: You get an 'access denied' page or are sent back — none of that screen's data is shown, even briefly. | G13: audit.log.view | H13: Not run
A14: lab_technician:url:/billing | B14: Must not see | C14: Finance | D14: Typing the address of Billing | E14: Type app.medbrains.in/billing into the address bar. | F14: You get an 'access denied' page or are sent back — none of that screen's data is shown, even briefly. | G14: billing.invoices.list | H14: Not run
A15: lab_technician:url:/mrd | B15: Must not see | C15: Operations | D15: Typing the address of Medical Records | E15: Type app.medbrains.in/mrd into the address bar. | F15: You get an 'access denied' page or are sent back — none of that screen's data is shown, even briefly. | H15: Not run
A16: lab_technician:wf:collect-a-sample-with-a-barcode | B16: Workflow | C16: Lab | D16: Collect a sample with a barcode | E16: (As test_doctor, order a CBC.) Lab → the order → Collect sample → scan/enter the patient's UHID and a tube barcode. | F16: Collection refuses a wrong UHID; on success the order shows 'sample collected' with the barcode. | H16: Not run
A17: lab_technician:wf:enter-and-verify-results | B17: Workflow | C17: Lab | D17: Enter and verify results | E17: Lab → the collected order → enter results → verify. | F17: Values outside range are flagged H/L; the doctor sees the verified result on the visit; a critical value raises an alert. | H17: Not run

Sheet Pharmacist
A1: Case | B1: Type | C1: Area | D1: What to test | E1: Steps | F1: Expected | G1: Permission | H1: Result | I1: Tester | J1: Date | K1: Notes
A2: pharmacist:sign-in | B2: Sign in | C2: Sign in | D2: Sign in as Pharmacist | E2: app.medbrains.in → hospital code AMH → username test_pharmacist and the password from your test-accounts file. | F2: You are signed in; the header shows 'TEST - Pharmacist'; you land on a page you can use (not an error). | H2: Not run
A3: pharmacist:see:/dashboard | B3: Should see | C3: Core | D3: Open Dashboard | E3: Menu → Core → Dashboard (/dashboard) | F3: The screen opens with no 'access denied' or error message. Lists load; an empty list says so. Buttons to add or change things appear only where this role should do that. | G3: dashboard.view | H3: Not run
A4: pharmacist:see:/approvals | B4: Should see | C4: Core | D4: Open Approvals | E4: Menu → Core → Approvals (/approvals) | F4: The screen opens with no 'access denied' or error message. Lists load; an empty list says so. Buttons to add or change things appear only where this role should do that. | H4: Not run
A5: pharmacist:see:/health-pulse | B5: Should see | C5: Core | D5: Open Health Pulse | E5: Menu → Core → Health Pulse (/health-pulse) | F5: The screen opens with no 'access denied' or error message. Lists load; an empty list says so. Buttons to add or change things appear only where this role should do that. | G5: dashboard.view | H5: Not run
A6: pharmacist:see:/ward-stock | B6: Should see | C6: Diagnostics | D6: Open Ward Stock | E6: Menu → Diagnostics → Ward Stock (/ward-stock) | F6: The screen opens with no 'access denied' or error message. Lists load; an empty list says so. Buttons to add or change things appear only where this role should do that. (Hidden if the hospital has this module switched off.) | G6: pharmacy.stores.manage | H6: Not run
A7: pharmacist:see:/pharmacy | B7: Should see | C7: Diagnostics | D7: Open Pharmacy | E7: Menu → Diagnostics → Pharmacy (/pharmacy) | F7: The screen opens with no 'access denied' or error message. Lists load; an empty list says so. Buttons to add or change things appear only where this role should do that. | G7: pharmacy.prescriptions.list | H7: Not run
A8: pharmacist:see:/pharmacy/finance | B8: Should see | C8: Diagnostics | D8: Open Pharmacy Finance | E8: Menu → Diagnostics → Pharmacy Finance (/pharmacy/finance) | F8: The screen opens with no 'access denied' or error message. Lists load; an empty list says so. Buttons to add or change things appear only where this role should do that. | G8: pharmacy_finance.cash_drawer.view, pharmacy_finance.cash_drawer.open, pharmacy_finance.cash_drawer.close… | H8: Not run
A9: pharmacist:see:/pharmacy/fulfilment | B9: Should see | C9: Diagnostics | D9: Open Fulfilment Queue | E9: Menu → Diagnostics → Fulfilment Queue (/pharmacy/fulfilment) | F9: The screen opens with no 'access denied' or error message. Lists load; an empty list says so. Buttons to add or change things appear only where this role should do that. (Hidden if the hospital has this module switched off.) | G9: pharmacy.fulfilment.pick | H9: Not run
A10: pharmacist:see:/pharmacy/deliveries | B10: Should see | C10: Diagnostics | D10: Open Home Deliveries | E10: Menu → Diagnostics → Home Deliveries (/pharmacy/deliveries) | F10: The screen opens with no 'access denied' or error message. Lists load; an empty list says so. Buttons to add or change things appear only where this role should do that. (Hidden if the hospital has this module switched off.) | G10: pharmacy.deliveries.view | H10: Not run
A11: pharmacist:see:/pharmacy/dispatch | B11: Should see | C11: Diagnostics | D11: Open Collection Counter | E11: Menu → Diagnostics → Collection Counter (/pharmacy/dispatch) | F11: The screen opens with no 'access denied' or error message. Lists load; an empty list says so. Buttons to add or change things appear only where this role should do that. (Hidden if the hospital has this module switched off.) | G11: pharmacy.fulfilment.dispatch | H11: Not run
A12: pharmacist:see:/indent | B12: Should see | C12: Finance | D12: Open Indent & Store | E12: Menu → Finance → Indent & Store (/indent) | F12: The screen opens with no 'access denied' or error message. Lists load; an empty list says so. Buttons to add or change things appear only where this role should do that. | G12: indent.list | H12: Not run
A13: pharmacist:see:/materials | B13: Should see | C13: Finance | D13: Open Materials | E13: Menu → Finance → Materials (/materials) | F13: The screen opens with no 'access denied' or error message. Lists load; an empty list says so. Buttons to add or change things appear only where this role should do that. | G13: indent.list, assets.list, procurement.vendors.list… | H13: Not run
A14: pharmacist:see:/lms | B14: Should see | C14: Operations | D14: Open Learning (LMS) | E14: Menu → Operations → Learning (LMS) (/lms) | F14: The screen opens with no 'access denied' or error message. Lists load; an empty list says so. Buttons to add or change things appear only where this role should do that. | G14: lms.my_learning.view | H14: Not run
A15: pharmacist:see:/regulatory | B15: Should see | C15: Compliance | D15: Open Regulatory Compliance | E15: Menu → Compliance → Regulatory Compliance (/regulatory) | F15: The screen opens with no 'access denied' or error message. Lists load; an empty list says so. Buttons to add or change things appear only where this role should do that. | G15: regulatory.dashboard.view | H15: Not run
A16: pharmacist:see:/reports | B16: Should see | C16: Compliance | D16: Open Reports Center | E16: Menu → Compliance → Reports Center (/reports) | F16: The screen opens with no 'access denied' or error message. Lists load; an empty list says so. Buttons to add or change things appear only where this role should do that. | G16: analytics.view, billing.reports.view, quality.indicators.list… | H16: Not run
A17: pharmacist:see:/admin/documents | B17: Should see | C17: Administration | D17: Open Documents & Printing | E17: Menu → Administration → Admin → Documents & Printing (/admin/documents) | F17: The screen opens with no 'access denied' or error message. Lists load; an empty list says so. Buttons to add or change things appear only where this role should do that. | G17: documents.templates.list | H17: Not run
A18: pharmacist:menu | B18: Must not see | C18: Menu | D18: Menu shows only this role's screens | E18: Look through every menu group. | F18: These must NOT be in the menu: Token Board, Token Console, Patients, OPD Queue, Appointments, Telemedicine, Doctor Sign-offs, Emergency, Order Sets, Chronic Care, Home healthcare, Home visits, Lab, Radiology, Blood Bank, IPD, Care View, Case sheet review, ICU, Nurse Activities, Operation Theatre, Diet & Kitchen, Bedside Portal, Billing, Insurance & TPA, Procurement, Payroll, Front Office, Smart Scheduling, Command Center, Communications, Camp Management, Ambulance, Housekeeping, CSSD, Facilities Management, Biomedical Engineering, Security, HR & Staffing, Medical Records, Clinical Knowledge, Directory, Hospital groups, Inter-hospital transfers, Inter-hospital stock, Marketing, Health packages, Testimonials, Micro-site settings, Quality, Infection Control, Consent Management, Analytics & Dashboards, Audit Trail, Utilization Review, Case Management, Ophthalmology, Dental, Cath Lab, Endoscopy, Psychiatry, Physical Medicine, Palliative Care, Maternity, Other Specialties, Clinical trials, Long-term care, Occupational Health, Users, Doctors, Roles & Permissions, Access Groups, Single Sign-On, Access Requests, NABH Indicators, Setup Center, Onboarding workbook, Settings, Document Templates, Built-in Pipelines, Forms, Test cycles, API keys, Webhooks, Doctor Schedules, Retrospective Entry, Device Integration, Paired Devices, Queues, Message Simulator. | H18: Not run
A19: pharmacist:url:/admin/users | B19: Must not see | C19: Administration | D19: Typing the address of Users | E19: Type app.medbrains.in/admin/users into the address bar. | F19: You get an 'access denied' page or are sent back — none of that screen's data is shown, even briefly. | G19: admin.users.list | H19: Not run
A20: pharmacist:url:/audit | B20: Must not see | C20: Compliance | D20: Typing the address of Audit Trail | E20: Type app.medbrains.in/audit into the address bar. | F20: You get an 'access denied' page or are sent back — none of that screen's data is shown, even briefly. | G20: audit.log.view | H20: Not run
A21: pharmacist:url:/billing | B21: Must not see | C21: Finance | D21: Typing the address of Billing | E21: Type app.medbrains.in/billing into the address bar. | F21: You get an 'access denied' page or are sent back — none of that screen's data is shown, even briefly. | G21: billing.invoices.list | H21: Not run
A22: pharmacist:url:/mrd | B22: Must not see | C22: Operations | D22: Typing the address of Medical Records | E22: Type app.medbrains.in/mrd into the address bar. | F22: You get an 'access denied' page or are sent back — none of that screen's data is shown, even briefly. | H22: Not run
A23: pharmacist:wf:dispense-a-prescription | B23: Workflow | C23: Pharmacy | D23: Dispense a prescription | E23: (As test_doctor, prescribe two medicines.) Pharmacy → prescription queue → open → dispense from the oldest-expiry batch. | F23: Stock reduces from the chosen batch; a label can be printed; the items are billed. | H23: Not run
A24: pharmacist:wf:controlled-schedule-h-drug | B24: Workflow | C24: Pharmacy | D24: Controlled / Schedule H drug | E24: Dispense a Schedule H or NDPS drug. | F24: The schedule badge shows; NDPS needs a register entry before it can be dispensed. | H24: Not run
A25: pharmacist:wf:counter-sale-and-a-return | B25: Workflow | C25: Pharmacy | D25: Counter sale and a return | E25: Pharmacy → POS → sell an OTC item → then return it. | F25: The sale prints a receipt; the return restores stock and refunds at the original price. | H25: Not run

Sheet Billing Clerk
A1: Case | B1: Type | C1: Area | D1: What to test | E1: Steps | F1: Expected | G1: Permission | H1: Result | I1: Tester | J1: Date | K1: Notes
A2: billing_clerk:sign-in | B2: Sign in | C2: Sign in | D2: Sign in as Billing Clerk | E2: app.medbrains.in → hospital code AMH → username test_billing_clerk and the password from your test-accounts file. | F2: You are signed in; the header shows 'TEST - Billing Clerk'; you land on a page you can use (not an error). | H2: Not run
A3: billing_clerk:see:/dashboard | B3: Should see | C3: Core | D3: Open Dashboard | E3: Menu → Core → Dashboard (/dashboard) | F3: The screen opens with no 'access denied' or error message. Lists load; an empty list says so. Buttons to add or change things appear only where this role should do that. | G3: dashboard.view | H3: Not run
A4: billing_clerk:see:/approvals | B4: Should see | C4: Core | D4: Open Approvals | E4: Menu → Core → Approvals (/approvals) | F4: The screen opens with no 'access denied' or error message. Lists load; an empty list says so. Buttons to add or change things appear only where this role should do that. | H4: Not run
A5: billing_clerk:see:/health-pulse | B5: Should see | C5: Core | D5: Open Health Pulse | E5: Menu → Core → Health Pulse (/health-pulse) | F5: The screen opens with no 'access denied' or error message. Lists load; an empty list says so. Buttons to add or change things appear only where this role should do that. | G5: dashboard.view | H5: Not run
A6: billing_clerk:see:/patients | B6: Should see | C6: Clinical | D6: Open Patients | E6: Menu → Clinical → Patients (/patients) | F6: The screen opens with no 'access denied' or error message. Lists load; an empty list says so. Buttons to add or change things appear only where this role should do that. | G6: patients.list | H6: Not run
A7: billing_clerk:see:/emergency | B7: Should see | C7: Clinical | D7: Open Emergency | E7: Menu → Clinical → Emergency (/emergency) | F7: The screen opens with no 'access denied' or error message. Lists load; an empty list says so. Buttons to add or change things appear only where this role should do that. | G7: emergency.visits.list | H7: Not run
A8: billing_clerk:see:/pharmacy/finance | B8: Should see | C8: Diagnostics | D8: Open Pharmacy Finance | E8: Menu → Diagnostics → Pharmacy Finance (/pharmacy/finance) | F8: The screen opens with no 'access denied' or error message. Lists load; an empty list says so. Buttons to add or change things appear only where this role should do that. | G8: pharmacy_finance.cash_drawer.view, pharmacy_finance.cash_drawer.open, pharmacy_finance.cash_drawer.close… | H8: Not run
A9: billing_clerk:see:/billing | B9: Should see | C9: Finance | D9: Open Billing | E9: Menu → Finance → Billing (/billing) | F9: The screen opens with no 'access denied' or error message. Lists load; an empty list says so. Buttons to add or change things appear only where this role should do that. | G9: billing.invoices.list | H9: Not run
A10: billing_clerk:see:/insurance | B10: Should see | C10: Finance | D10: Open Insurance & TPA | E10: Menu → Finance → Insurance & TPA (/insurance) | F10: The screen opens with no 'access denied' or error message. Lists load; an empty list says so. Buttons to add or change things appear only where this role should do that. | G10: insurance.verification.list | H10: Not run
A11: billing_clerk:see:/front-office | B11: Should see | C11: Operations | D11: Open Front Office | E11: Menu → Operations → Front Office (/front-office) | F11: The screen opens with no 'access denied' or error message. Lists load; an empty list says so. Buttons to add or change things appear only where this role should do that. | G11: front_office.visitors.list, front_office.visitors.create, front_office.visitors.manage… | H11: Not run
A12: billing_clerk:see:/lms | B12: Should see | C12: Operations | D12: Open Learning (LMS) | E12: Menu → Operations → Learning (LMS) (/lms) | F12: The screen opens with no 'access denied' or error message. Lists load; an empty list says so. Buttons to add or change things appear only where this role should do that. | G12: lms.my_learning.view | H12: Not run
A13: billing_clerk:see:/health-packages | B13: Should see | C13: Marketing & Web | D13: Open Health packages | E13: Menu → Marketing & Web → Health packages (/health-packages) | F13: The screen opens with no 'access denied' or error message. Lists load; an empty list says so. Buttons to add or change things appear only where this role should do that. | G13: specialty.health_packages.list | H13: Not run
A14: billing_clerk:see:/testimonials | B14: Should see | C14: Marketing & Web | D14: Open Testimonials | E14: Menu → Marketing & Web → Testimonials (/testimonials) | F14: The screen opens with no 'access denied' or error message. Lists load; an empty list says so. Buttons to add or change things appear only where this role should do that. | G14: specialty.health_packages.list | H14: Not run
A15: billing_clerk:see:/microsite-settings | B15: Should see | C15: Marketing & Web | D15: Open Micro-site settings | E15: Menu → Marketing & Web → Micro-site settings (/microsite-settings) | F15: The screen opens with no 'access denied' or error message. Lists load; an empty list says so. Buttons to add or change things appear only where this role should do that. | G15: specialty.health_packages.list | H15: Not run
A16: billing_clerk:see:/reports | B16: Should see | C16: Compliance | D16: Open Reports Center | E16: Menu → Compliance → Reports Center (/reports) | F16: The screen opens with no 'access denied' or error message. Lists load; an empty list says so. Buttons to add or change things appear only where this role should do that. | G16: analytics.view, billing.reports.view, quality.indicators.list… | H16: Not run
A17: billing_clerk:see:/admin/documents | B17: Should see | C17: Administration | D17: Open Documents & Printing | E17: Menu → Administration → Admin → Documents & Printing (/admin/documents) | F17: The screen opens with no 'access denied' or error message. Lists load; an empty list says so. Buttons to add or change things appear only where this role should do that. | G17: documents.templates.list | H17: Not run
A18: billing_clerk:menu | B18: Must not see | C18: Menu | D18: Menu shows only this role's screens | E18: Look through every menu group. | F18: These must NOT be in the menu: Token Board, Token Console, OPD Queue, Appointments, Telemedicine, Doctor Sign-offs, Order Sets, Chronic Care, Home healthcare, Home visits, Lab, Radiology, Ward Stock, Pharmacy, Fulfilment Queue, Home Deliveries, Collection Counter, Blood Bank, IPD, Care View, Case sheet review, ICU, Nurse Activities, Operation Theatre, Diet & Kitchen, Bedside Portal, Procurement, Indent & Store, Materials, Payroll, Smart Scheduling, Command Center, Communications, Camp Management, Ambulance, Housekeeping, CSSD, Facilities Management, Biomedical Engineering, Security, HR & Staffing, Medical Records, Clinical Knowledge, Directory, Hospital groups, Inter-hospital transfers, Inter-hospital stock, Marketing, Quality, Infection Control, Consent Management, Regulatory Compliance, Analytics & Dashboards, Audit Trail, Utilization Review, Case Management, Ophthalmology, Dental, Cath Lab, Endoscopy, Psychiatry, Physical Medicine, Palliative Care, Maternity, Other Specialties, Clinical trials, Long-term care, Occupational Health, Users, Doctors, Roles & Permissions, Access Groups, Single Sign-On, Access Requests, NABH Indicators, Setup Center, Onboarding workbook, Settings, Document Templates, Built-in Pipelines, Forms, Test cycles, API keys, Webhooks, Doctor Schedules, Retrospective Entry, Device Integration, Paired Devices, Queues, Message Simulator. | H18: Not run
A19: billing_clerk:url:/admin/users | B19: Must not see | C19: Administration | D19: Typing the address of Users | E19: Type app.medbrains.in/admin/users into the address bar. | F19: You get an 'access denied' page or are sent back — none of that screen's data is shown, even briefly. | G19: admin.users.list | H19: Not run
A20: billing_clerk:url:/audit | B20: Must not see | C20: Compliance | D20: Typing the address of Audit Trail | E20: Type app.medbrains.in/audit into the address bar. | F20: You get an 'access denied' page or are sent back — none of that screen's data is shown, even briefly. | G20: audit.log.view | H20: Not run
A21: billing_clerk:url:/mrd | B21: Must not see | C21: Operations | D21: Typing the address of Medical Records | E21: Type app.medbrains.in/mrd into the address bar. | F21: You get an 'access denied' page or are sent back — none of that screen's data is shown, even briefly. | H21: Not run
A22: billing_clerk:url:/pharmacy | B22: Must not see | C22: Diagnostics | D22: Typing the address of Pharmacy | E22: Type app.medbrains.in/pharmacy into the address bar. | F22: You get an 'access denied' page or are sent back — none of that screen's data is shown, even briefly. | G22: pharmacy.prescriptions.list | H22: Not run
A23: billing_clerk:wf:collect-payment-on-an-opd-bill | B23: Workflow | C23: Billing | D23: Collect payment on an OPD bill | E23: Billing → find the patient's bill → Record payment (cash or UPI) → print receipt. | F23: The bill shows paid; the receipt prints; the day's collection includes it. | H23: Not run
A24: billing_clerk:wf:open-a-bill-raised-by-someone-else | B24: Workflow | C24: Billing | D24: Open a bill raised by someone else | E24: Open a bill created by another user or by auto-billing. | F24: It opens. (A 'could not be opened' message here is a defect.) | H24: Not run
A25: billing_clerk:wf:split-an-insured-bill-payer-split | B25: Workflow | C25: Billing | D25: Split an insured bill (payer split) | E25: An issued bill with an insurance claim → Payer split. Check the admission kit is marked Patient (IRDAI). Move one line to Patient with a reason → Write to claim → Patient share PDF. | F25: Insurer and patient totals add up to the bill; the claim amount updates; moving a line without a reason is refused. | H25: Not run

Sheet Housekeeping Staff
A1: Case | B1: Type | C1: Area | D1: What to test | E1: Steps | F1: Expected | G1: Permission | H1: Result | I1: Tester | J1: Date | K1: Notes
A2: housekeeping_staff:sign-in | B2: Sign in | C2: Sign in | D2: Sign in as Housekeeping Staff | E2: app.medbrains.in → hospital code AMH → username test_housekeeping_staff and the password from your test-accounts file. | F2: You are signed in; the header shows 'TEST - Housekeeping Staff'; you land on a page you can use (not an error). | H2: Not run
A3: housekeeping_staff:see:/dashboard | B3: Should see | C3: Core | D3: Open Dashboard | E3: Menu → Core → Dashboard (/dashboard) | F3: The screen opens with no 'access denied' or error message. Lists load; an empty list says so. Buttons to add or change things appear only where this role should do that. | G3: dashboard.view | H3: Not run
A4: housekeeping_staff:see:/approvals | B4: Should see | C4: Core | D4: Open Approvals | E4: Menu → Core → Approvals (/approvals) | F4: The screen opens with no 'access denied' or error message. Lists load; an empty list says so. Buttons to add or change things appear only where this role should do that. | H4: Not run
A5: housekeeping_staff:see:/health-pulse | B5: Should see | C5: Core | D5: Open Health Pulse | E5: Menu → Core → Health Pulse (/health-pulse) | F5: The screen opens with no 'access denied' or error message. Lists load; an empty list says so. Buttons to add or change things appear only where this role should do that. | G5: dashboard.view | H5: Not run
A6: housekeeping_staff:see:/housekeeping | B6: Should see | C6: Operations | D6: Open Housekeeping | E6: Menu → Operations → Housekeeping (/housekeeping) | F6: The screen opens with no 'access denied' or error message. Lists load; an empty list says so. Buttons to add or change things appear only where this role should do that. | G6: housekeeping.cleaning.list | H6: Not run
A7: housekeeping_staff:see:/lms | B7: Should see | C7: Operations | D7: Open Learning (LMS) | E7: Menu → Operations → Learning (LMS) (/lms) | F7: The screen opens with no 'access denied' or error message. Lists load; an empty list says so. Buttons to add or change things appear only where this role should do that. | G7: lms.my_learning.view | H7: Not run
A8: housekeeping_staff:menu | B8: Must not see | C8: Menu | D8: Menu shows only this role's screens | E8: Look through every menu group. | F8: These must NOT be in the menu: Token Board, Token Console, Patients, OPD Queue, Appointments, Telemedicine, Doctor Sign-offs, Emergency, Order Sets, Chronic Care, Home healthcare, Home visits, Lab, Radiology, Ward Stock, Pharmacy, Pharmacy Finance, Fulfilment Queue, Home Deliveries, Collection Counter, Blood Bank, IPD, Care View, Case sheet review, ICU, Nurse Activities, Operation Theatre, Diet & Kitchen, Bedside Portal, Billing, Insurance & TPA, Procurement, Indent & Store, Materials, Payroll, Front Office, Smart Scheduling, Command Center, Communications, Camp Management, Ambulance, CSSD, Facilities Management, Biomedical Engineering, Security, HR & Staffing, Medical Records, Clinical Knowledge, Directory, Hospital groups, Inter-hospital transfers, Inter-hospital stock, Marketing, Health packages, Testimonials, Micro-site settings, Quality, Infection Control, Consent Management, Regulatory Compliance, Analytics & Dashboards, Reports Center, Audit Trail, Utilization Review, Case Management, Ophthalmology, Dental, Cath Lab, Endoscopy, Psychiatry, Physical Medicine, Palliative Care, Maternity, Other Specialties, Clinical trials, Long-term care, Occupational Health, Users, Doctors, Roles & Permissions, Access Groups, Single Sign-On, Access Requests, NABH Indicators, Setup Center, Onboarding workbook, Settings, Document Templates, Built-in Pipelines, Forms, Test cycles, API keys, Webhooks, Doctor Schedules, Documents & Printing, Retrospective Entry, Device Integration, Paired Devices, Queues, Message Simulator. | H8: Not run
A9: housekeeping_staff:url:/admin/users | B9: Must not see | C9: Administration | D9: Typing the address of Users | E9: Type app.medbrains.in/admin/users into the address bar. | F9: You get an 'access denied' page or are sent back — none of that screen's data is shown, even briefly. | G9: admin.users.list | H9: Not run
A10: housekeeping_staff:url:/audit | B10: Must not see | C10: Compliance | D10: Typing the address of Audit Trail | E10: Type app.medbrains.in/audit into the address bar. | F10: You get an 'access denied' page or are sent back — none of that screen's data is shown, even briefly. | G10: audit.log.view | H10: Not run
A11: housekeeping_staff:url:/billing | B11: Must not see | C11: Finance | D11: Typing the address of Billing | E11: Type app.medbrains.in/billing into the address bar. | F11: You get an 'access denied' page or are sent back — none of that screen's data is shown, even briefly. | G11: billing.invoices.list | H11: Not run
A12: housekeeping_staff:url:/mrd | B12: Must not see | C12: Operations | D12: Typing the address of Medical Records | E12: Type app.medbrains.in/mrd into the address bar. | F12: You get an 'access denied' page or are sent back — none of that screen's data is shown, even briefly. | H12: Not run
A13: housekeeping_staff:wf:clean-a-vacated-bed | B13: Workflow | C13: Housekeeping | D13: Clean a vacated bed | E13: Housekeeping → a bed marked for cleaning → start → done. | F13: The bed becomes available for admission. | H13: Not run

Sheet Facilities Manager
A1: Case | B1: Type | C1: Area | D1: What to test | E1: Steps | F1: Expected | G1: Permission | H1: Result | I1: Tester | J1: Date | K1: Notes
A2: facilities_manager:sign-in | B2: Sign in | C2: Sign in | D2: Sign in as Facilities Manager | E2: app.medbrains.in → hospital code AMH → username test_facilities_manager and the password from your test-accounts file. | F2: You are signed in; the header shows 'TEST - Facilities Manager'; you land on a page you can use (not an error). | H2: Not run
A3: facilities_manager:see:/dashboard | B3: Should see | C3: Core | D3: Open Dashboard | E3: Menu → Core → Dashboard (/dashboard) | F3: The screen opens with no 'access denied' or error message. Lists load; an empty list says so. Buttons to add or change things appear only where this role should do that. | G3: dashboard.view | H3: Not run
A4: facilities_manager:see:/approvals | B4: Should see | C4: Core | D4: Open Approvals | E4: Menu → Core → Approvals (/approvals) | F4: The screen opens with no 'access denied' or error message. Lists load; an empty list says so. Buttons to add or change things appear only where this role should do that. | H4: Not run
A5: facilities_manager:see:/health-pulse | B5: Should see | C5: Core | D5: Open Health Pulse | E5: Menu → Core → Health Pulse (/health-pulse) | F5: The screen opens with no 'access denied' or error message. Lists load; an empty list says so. Buttons to add or change things appear only where this role should do that. | G5: dashboard.view | H5: Not run
A6: facilities_manager:see:/indent | B6: Should see | C6: Finance | D6: Open Indent & Store | E6: Menu → Finance → Indent & Store (/indent) | F6: The screen opens with no 'access denied' or error message. Lists load; an empty list says so. Buttons to add or change things appear only where this role should do that. | G6: indent.list | H6: Not run
A7: facilities_manager:see:/materials | B7: Should see | C7: Finance | D7: Open Materials | E7: Menu → Finance → Materials (/materials) | F7: The screen opens with no 'access denied' or error message. Lists load; an empty list says so. Buttons to add or change things appear only where this role should do that. | G7: indent.list, assets.list, procurement.vendors.list… | H7: Not run
A8: facilities_manager:see:/housekeeping | B8: Should see | C8: Operations | D8: Open Housekeeping | E8: Menu → Operations → Housekeeping (/housekeeping) | F8: The screen opens with no 'access denied' or error message. Lists load; an empty list says so. Buttons to add or change things appear only where this role should do that. | G8: housekeeping.cleaning.list | H8: Not run
A9: facilities_manager:see:/facilities | B9: Should see | C9: Operations | D9: Open Facilities Management | E9: Menu → Operations → Facilities Management (/facilities) | F9: The screen opens with no 'access denied' or error message. Lists load; an empty list says so. Buttons to add or change things appear only where this role should do that. | G9: facilities.gas.list | H9: Not run
A10: facilities_manager:see:/bme | B10: Should see | C10: Operations | D10: Open Biomedical Engineering | E10: Menu → Operations → Biomedical Engineering (/bme) | F10: The screen opens with no 'access denied' or error message. Lists load; an empty list says so. Buttons to add or change things appear only where this role should do that. | G10: bme.equipment.list | H10: Not run
A11: facilities_manager:see:/hr | B11: Should see | C11: Operations | D11: Open HR & Staffing | E11: Menu → Operations → HR & Staffing (/hr) | F11: The screen opens with no 'access denied' or error message. Lists load; an empty list says so. Buttons to add or change things appear only where this role should do that. | G11: hr.employees.list | H11: Not run
A12: facilities_manager:see:/lms | B12: Should see | C12: Operations | D12: Open Learning (LMS) | E12: Menu → Operations → Learning (LMS) (/lms) | F12: The screen opens with no 'access denied' or error message. Lists load; an empty list says so. Buttons to add or change things appear only where this role should do that. | G12: lms.my_learning.view | H12: Not run
A13: facilities_manager:see:/regulatory | B13: Should see | C13: Compliance | D13: Open Regulatory Compliance | E13: Menu → Compliance → Regulatory Compliance (/regulatory) | F13: The screen opens with no 'access denied' or error message. Lists load; an empty list says so. Buttons to add or change things appear only where this role should do that. | G13: regulatory.dashboard.view | H13: Not run
A14: facilities_manager:see:/reports | B14: Should see | C14: Compliance | D14: Open Reports Center | E14: Menu → Compliance → Reports Center (/reports) | F14: The screen opens with no 'access denied' or error message. Lists load; an empty list says so. Buttons to add or change things appear only where this role should do that. | G14: analytics.view, billing.reports.view, quality.indicators.list… | H14: Not run
A15: facilities_manager:see:/admin/integration-hub | B15: Should see | C15: Administration | D15: Open Built-in Pipelines | E15: Menu → Administration → Admin → Built-in Pipelines (/admin/integration-hub) | F15: The screen opens with no 'access denied' or error message. Lists load; an empty list says so. Buttons to add or change things appear only where this role should do that. | G15: integration.list | H15: Not run
A16: facilities_manager:see:/admin/documents | B16: Should see | C16: Administration | D16: Open Documents & Printing | E16: Menu → Administration → Admin → Documents & Printing (/admin/documents) | F16: The screen opens with no 'access denied' or error message. Lists load; an empty list says so. Buttons to add or change things appear only where this role should do that. | G16: documents.templates.list | H16: Not run
A17: facilities_manager:menu | B17: Must not see | C17: Menu | D17: Menu shows only this role's screens | E17: Look through every menu group. | F17: These must NOT be in the menu: Token Board, Token Console, Patients, OPD Queue, Appointments, Telemedicine, Doctor Sign-offs, Emergency, Order Sets, Chronic Care, Home healthcare, Home visits, Lab, Radiology, Ward Stock, Pharmacy, Pharmacy Finance, Fulfilment Queue, Home Deliveries, Collection Counter, Blood Bank, IPD, Care View, Case sheet review, ICU, Nurse Activities, Operation Theatre, Diet & Kitchen, Bedside Portal, Billing, Insurance & TPA, Procurement, Payroll, Front Office, Smart Scheduling, Command Center, Communications, Camp Management, Ambulance, CSSD, Security, Medical Records, Clinical Knowledge, Directory, Hospital groups, Inter-hospital transfers, Inter-hospital stock, Marketing, Health packages, Testimonials, Micro-site settings, Quality, Infection Control, Consent Management, Analytics & Dashboards, Audit Trail, Utilization Review, Case Management, Ophthalmology, Dental, Cath Lab, Endoscopy, Psychiatry, Physical Medicine, Palliative Care, Maternity, Other Specialties, Clinical trials, Long-term care, Occupational Health, Users, Doctors, Roles & Permissions, Access Groups, Single Sign-On, Access Requests, NABH Indicators, Setup Center, Onboarding workbook, Settings, Document Templates, Forms, Test cycles, API keys, Webhooks, Doctor Schedules, Retrospective Entry, Device Integration, Paired Devices, Queues, Message Simulator. | H17: Not run
A18: facilities_manager:url:/admin/users | B18: Must not see | C18: Administration | D18: Typing the address of Users | E18: Type app.medbrains.in/admin/users into the address bar. | F18: You get an 'access denied' page or are sent back — none of that screen's data is shown, even briefly. | G18: admin.users.list | H18: Not run
A19: facilities_manager:url:/audit | B19: Must not see | C19: Compliance | D19: Typing the address of Audit Trail | E19: Type app.medbrains.in/audit into the address bar. | F19: You get an 'access denied' page or are sent back — none of that screen's data is shown, even briefly. | G19: audit.log.view | H19: Not run
A20: facilities_manager:url:/billing | B20: Must not see | C20: Finance | D20: Typing the address of Billing | E20: Type app.medbrains.in/billing into the address bar. | F20: You get an 'access denied' page or are sent back — none of that screen's data is shown, even briefly. | G20: billing.invoices.list | H20: Not run
A21: facilities_manager:url:/mrd | B21: Must not see | C21: Operations | D21: Typing the address of Medical Records | E21: Type app.medbrains.in/mrd into the address bar. | F21: You get an 'access denied' page or are sent back — none of that screen's data is shown, even briefly. | H21: Not run
A22: facilities_manager:wf:raise-and-close-a-work-order | B22: Workflow | C22: Facilities Management | D22: Raise and close a work order | E22: Facilities Management → new work order → assign → complete. | F22: The order moves through its states with times recorded. | H22: Not run

Sheet Audit Officer
A1: Case | B1: Type | C1: Area | D1: What to test | E1: Steps | F1: Expected | G1: Permission | H1: Result | I1: Tester | J1: Date | K1: Notes
A2: audit_officer:sign-in | B2: Sign in | C2: Sign in | D2: Sign in as Audit Officer | E2: app.medbrains.in → hospital code AMH → username test_audit_officer and the password from your test-accounts file. | F2: You are signed in; the header shows 'TEST - Audit Officer'; you land on a page you can use (not an error). | H2: Not run
A3: audit_officer:see:/dashboard | B3: Should see | C3: Core | D3: Open Dashboard | E3: Menu → Core → Dashboard (/dashboard) | F3: The screen opens with no 'access denied' or error message. Lists load; an empty list says so. Buttons to add or change things appear only where this role should do that. | G3: dashboard.view | H3: Not run
A4: audit_officer:see:/approvals | B4: Should see | C4: Core | D4: Open Approvals | E4: Menu → Core → Approvals (/approvals) | F4: The screen opens with no 'access denied' or error message. Lists load; an empty list says so. Buttons to add or change things appear only where this role should do that. | H4: Not run
A5: audit_officer:see:/health-pulse | B5: Should see | C5: Core | D5: Open Health Pulse | E5: Menu → Core → Health Pulse (/health-pulse) | F5: The screen opens with no 'access denied' or error message. Lists load; an empty list says so. Buttons to add or change things appear only where this role should do that. | G5: dashboard.view | H5: Not run
A6: audit_officer:see:/patients | B6: Should see | C6: Clinical | D6: Open Patients | E6: Menu → Clinical → Patients (/patients) | F6: The screen opens with no 'access denied' or error message. Lists load; an empty list says so. Buttons to add or change things appear only where this role should do that. | G6: patients.list | H6: Not run
A7: audit_officer:see:/opd | B7: Should see | C7: Clinical | D7: Open OPD Queue | E7: Menu → Clinical → OPD Queue (/opd) | F7: The screen opens with no 'access denied' or error message. Lists load; an empty list says so. Buttons to add or change things appear only where this role should do that. | G7: opd.queue.list | H7: Not run
A8: audit_officer:see:/telemedicine | B8: Should see | C8: Clinical | D8: Open Telemedicine | E8: Menu → Clinical → Telemedicine (/telemedicine) | F8: The screen opens with no 'access denied' or error message. Lists load; an empty list says so. Buttons to add or change things appear only where this role should do that. | G8: opd.queue.view | H8: Not run
A9: audit_officer:see:/emergency | B9: Should see | C9: Clinical | D9: Open Emergency | E9: Menu → Clinical → Emergency (/emergency) | F9: The screen opens with no 'access denied' or error message. Lists load; an empty list says so. Buttons to add or change things appear only where this role should do that. | G9: emergency.visits.list | H9: Not run
A10: audit_officer:see:/lab | B10: Should see | C10: Diagnostics | D10: Open Lab | E10: Menu → Diagnostics → Lab (/lab) | F10: The screen opens with no 'access denied' or error message. Lists load; an empty list says so. Buttons to add or change things appear only where this role should do that. (Hidden if the hospital has this module switched off.) | G10: lab.orders.list | H10: Not run
A11: audit_officer:see:/pharmacy | B11: Should see | C11: Diagnostics | D11: Open Pharmacy | E11: Menu → Diagnostics → Pharmacy (/pharmacy) | F11: The screen opens with no 'access denied' or error message. Lists load; an empty list says so. Buttons to add or change things appear only where this role should do that. | G11: pharmacy.prescriptions.list | H11: Not run
A12: audit_officer:see:/ipd | B12: Should see | C12: Inpatient | D12: Open IPD | E12: Menu → Inpatient → IPD (/ipd) | F12: The screen opens with no 'access denied' or error message. Lists load; an empty list says so. Buttons to add or change things appear only where this role should do that. | G12: ipd.admissions.list | H12: Not run
A13: audit_officer:see:/case-sheet-review | B13: Should see | C13: Inpatient | D13: Open Case sheet review | E13: Menu → Inpatient → Case sheet review (/case-sheet-review) | F13: The screen opens with no 'access denied' or error message. Lists load; an empty list says so. Buttons to add or change things appear only where this role should do that. | G13: mrd.case_sheets.view | H13: Not run
A14: audit_officer:see:/billing | B14: Should see | C14: Finance | D14: Open Billing | E14: Menu → Finance → Billing (/billing) | F14: The screen opens with no 'access denied' or error message. Lists load; an empty list says so. Buttons to add or change things appear only where this role should do that. | G14: billing.invoices.list | H14: Not run
A15: audit_officer:see:/camp | B15: Should see | C15: Operations | D15: Open Camp Management | E15: Menu → Operations → Camp Management (/camp) | F15: The screen opens with no 'access denied' or error message. Lists load; an empty list says so. Buttons to add or change things appear only where this role should do that. | G15: camp.list | H15: Not run
A16: audit_officer:see:/security | B16: Should see | C16: Operations | D16: Open Security | E16: Menu → Operations → Security (/security) | F16: The screen opens with no 'access denied' or error message. Lists load; an empty list says so. Buttons to add or change things appear only where this role should do that. | G16: security.access.list | H16: Not run
... A24: audit_officer:see:/admin/documents | B24: Should see | C24: Administration | D24: Open Documents & Printing | E24: Menu → Administration → Admin → Documents & Printing (/admin/documents) | F24: The screen opens with no 'access denied' or error message. Lists load; an empty list says so. Buttons to add or change things appear only where this role should do that. | G24: documents.templates.list | H24: Not run
A25: audit_officer:menu | B25: Must not see | C25: Menu | D25: Menu shows only this role's screens | E25: Look through every menu group. | F25: These must NOT be in the menu: Token Board, Token Console, Appointments, Doctor Sign-offs, Order Sets, Chronic Care, Home healthcare, Home visits, Radiology, Ward Stock, Pharmacy Finance, Fulfilment Queue, Home Deliveries, Collection Counter, Blood Bank, Care View, ICU, Nurse Activities, Operation Theatre, Diet & Kitchen, Bedside Portal, Insurance & TPA, Procurement, Indent & Store, Materials, Payroll, Front Office, Smart Scheduling, Command Center, Communications, Ambulance, Housekeeping, CSSD, Facilities Management, Biomedical Engineering, HR & Staffing, Clinical Knowledge, Directory, Hospital groups, Inter-hospital transfers, Inter-hospital stock, Marketing, Health packages, Testimonials, Micro-site settings, Quality, Infection Control, Analytics & Dashboards, Utilization Review, Case Management, Ophthalmology, Dental, Cath Lab, Endoscopy, Psychiatry, Physical Medicine, Palliative Care, Maternity, Other Specialties, Clinical trials, Long-term care, Occupational Health, Users, Doctors, Roles & Permissions, Access Groups, Single Sign-On, NABH Indicators, Setup Center, Onboarding workbook, Settings, Document Templates, Built-in Pipelines, Forms, Test cycles, API keys, Webhooks, Doctor Schedules, Retrospective Entry, Device Integration, Paired Devices, Queues, Message Simulator. | H25: Not run
A26: audit_officer:url:/admin/users | B26: Must not see | C26: Administration | D26: Typing the address of Users | E26: Type app.medbrains.in/admin/users into the address bar. | F26: You get an 'access denied' page or are sent back — none of that screen's data is shown, even briefly. | G26: admin.users.list | H26: Not run
A27: audit_officer:url:/hr/payroll | B27: Must not see | C27: Finance | D27: Typing the address of Payroll | E27: Type app.medbrains.in/hr/payroll into the address bar. | F27: You get an 'access denied' page or are sent back — none of that screen's data is shown, even briefly. | G27: hr.payroll.structures.list | H27: Not run
A28: audit_officer:wf:trace-who-opened-a-record | B28: Workflow | C28: Audit Trail | D28: Trace who opened a record | E28: Audit Trail → filter by a test patient or a test user. | F28: Every view and change is listed with user, time and address; nothing can be edited or deleted. | H28: Not run

Sheet Quality Officer
A1: Case | B1: Type | C1: Area | D1: What to test | E1: Steps | F1: Expected | G1: Permission | H1: Result | I1: Tester | J1: Date | K1: Notes
A2: quality_officer:sign-in | B2: Sign in | C2: Sign in | D2: Sign in as Quality Officer | E2: app.medbrains.in → hospital code AMH → username test_quality_officer and the password from your test-accounts file. | F2: You are signed in; the header shows 'TEST - Quality Officer'; you land on a page you can use (not an error). | H2: Not run
A3: quality_officer:see:/dashboard | B3: Should see | C3: Core | D3: Open Dashboard | E3: Menu → Core → Dashboard (/dashboard) | F3: The screen opens with no 'access denied' or error message. Lists load; an empty list says so. Buttons to add or change things appear only where this role should do that. | G3: dashboard.view | H3: Not run
A4: quality_officer:see:/approvals | B4: Should see | C4: Core | D4: Open Approvals | E4: Menu → Core → Approvals (/approvals) | F4: The screen opens with no 'access denied' or error message. Lists load; an empty list says so. Buttons to add or change things appear only where this role should do that. | H4: Not run
A5: quality_officer:see:/health-pulse | B5: Should see | C5: Core | D5: Open Health Pulse | E5: Menu → Core → Health Pulse (/health-pulse) | F5: The screen opens with no 'access denied' or error message. Lists load; an empty list says so. Buttons to add or change things appear only where this role should do that. | G5: dashboard.view | H5: Not run
A6: quality_officer:see:/order-sets | B6: Should see | C6: Clinical | D6: Open Order Sets | E6: Menu → Clinical → Order Sets (/order-sets) | F6: The screen opens with no 'access denied' or error message. Lists load; an empty list says so. Buttons to add or change things appear only where this role should do that. | G6: order_sets.templates.list | H6: Not run
A7: quality_officer:see:/lab | B7: Should see | C7: Diagnostics | D7: Open Lab | E7: Menu → Diagnostics → Lab (/lab) | F7: The screen opens with no 'access denied' or error message. Lists load; an empty list says so. Buttons to add or change things appear only where this role should do that. (Hidden if the hospital has this module switched off.) | G7: lab.orders.list | H7: Not run
A8: quality_officer:see:/lms | B8: Should see | C8: Operations | D8: Open Learning (LMS) | E8: Menu → Operations → Learning (LMS) (/lms) | F8: The screen opens with no 'access denied' or error message. Lists load; an empty list says so. Buttons to add or change things appear only where this role should do that. | G8: lms.my_learning.view | H8: Not run
A9: quality_officer:see:/quality | B9: Should see | C9: Compliance | D9: Open Quality | E9: Menu → Compliance → Quality (/quality) | F9: The screen opens with no 'access denied' or error message. Lists load; an empty list says so. Buttons to add or change things appear only where this role should do that. | G9: quality.indicators.list | H9: Not run
A10: quality_officer:see:/regulatory | B10: Should see | C10: Compliance | D10: Open Regulatory Compliance | E10: Menu → Compliance → Regulatory Compliance (/regulatory) | F10: The screen opens with no 'access denied' or error message. Lists load; an empty list says so. Buttons to add or change things appear only where this role should do that. | G10: regulatory.dashboard.view | H10: Not run
A11: quality_officer:see:/reports | B11: Should see | C11: Compliance | D11: Open Reports Center | E11: Menu → Compliance → Reports Center (/reports) | F11: The screen opens with no 'access denied' or error message. Lists load; an empty list says so. Buttons to add or change things appear only where this role should do that. | G11: analytics.view, billing.reports.view, quality.indicators.list… | H11: Not run
A12: quality_officer:see:/clinical-trials | B12: Should see | C12: Specialty | D12: Open Clinical trials | E12: Menu → Specialty → Clinical trials (/clinical-trials) | F12: The screen opens with no 'access denied' or error message. Lists load; an empty list says so. Buttons to add or change things appear only where this role should do that. | G12: specialty.clinical_trials.list | H12: Not run
A13: quality_officer:see:/admin/nabh-indicators | B13: Should see | C13: Administration | D13: Open NABH Indicators | E13: Menu → Administration → Admin → NABH Indicators (/admin/nabh-indicators) | F13: The screen opens with no 'access denied' or error message. Lists load; an empty list says so. Buttons to add or change things appear only where this role should do that. | G13: quality.indicators.list | H13: Not run
A14: quality_officer:see:/admin/test-cycles | B14: Should see | C14: Administration | D14: Open Test cycles | E14: Menu → Administration → Admin → Test cycles (/admin/test-cycles) | F14: The screen opens with no 'access denied' or error message. Lists load; an empty list says so. Buttons to add or change things appear only where this role should do that. | G14: qa.test_cycles.manage | H14: Not run
A15: quality_officer:menu | B15: Must not see | C15: Menu | D15: Menu shows only this role's screens | E15: Look through every menu group. | F15: These must NOT be in the menu: Token Board, Token Console, Patients, OPD Queue, Appointments, Telemedicine, Doctor Sign-offs, Emergency, Chronic Care, Home healthcare, Home visits, Radiology, Ward Stock, Pharmacy, Pharmacy Finance, Fulfilment Queue, Home Deliveries, Collection Counter, Blood Bank, IPD, Care View, Case sheet review, ICU, Nurse Activities, Operation Theatre, Diet & Kitchen, Bedside Portal, Billing, Insurance & TPA, Procurement, Indent & Store, Materials, Payroll, Front Office, Smart Scheduling, Command Center, Communications, Camp Management, Ambulance, Housekeeping, CSSD, Facilities Management, Biomedical Engineering, Security, HR & Staffing, Medical Records, Clinical Knowledge, Directory, Hospital groups, Inter-hospital transfers, Inter-hospital stock, Marketing, Health packages, Testimonials, Micro-site settings, Infection Control, Consent Management, Analytics & Dashboards, Audit Trail, Utilization Review, Case Management, Ophthalmology, Dental, Cath Lab, Endoscopy, Psychiatry, Physical Medicine, Palliative Care, Maternity, Other Specialties, Long-term care, Occupational Health, Users, Doctors, Roles & Permissions, Access Groups, Single Sign-On, Access Requests, Setup Center, Onboarding workbook, Settings, Document Templates, Built-in Pipelines, Forms, API keys, Webhooks, Doctor Schedules, Documents & Printing, Retrospective Entry, Device Integration, Paired Devices, Queues, Message Simulator. | H15: Not run
A16: quality_officer:url:/admin/users | B16: Must not see | C16: Administration | D16: Typing the address of Users | E16: Type app.medbrains.in/admin/users into the address bar. | F16: You get an 'access denied' page or are sent back — none of that screen's data is shown, even briefly. | G16: admin.users.list | H16: Not run
A17: quality_officer:url:/audit | B17: Must not see | C17: Compliance | D17: Typing the address of Audit Trail | E17: Type app.medbrains.in/audit into the address bar. | F17: You get an 'access denied' page or are sent back — none of that screen's data is shown, even briefly. | G17: audit.log.view | H17: Not run
A18: quality_officer:url:/billing | B18: Must not see | C18: Finance | D18: Typing the address of Billing | E18: Type app.medbrains.in/billing into the address bar. | F18: You get an 'access denied' page or are sent back — none of that screen's data is shown, even briefly. | G18: billing.invoices.list | H18: Not run
A19: quality_officer:url:/mrd | B19: Must not see | C19: Operations | D19: Typing the address of Medical Records | E19: Type app.medbrains.in/mrd into the address bar. | F19: You get an 'access denied' page or are sent back — none of that screen's data is shown, even briefly. | H19: Not run
A20: quality_officer:wf:report-and-review-an-incident | B20: Workflow | C20: Quality | D20: Report and review an incident | E20: Quality → report an incident → review it. | F20: The incident is tracked to closure; NABH indicators reflect it. | H20: Not run

Sheet Occupational Health Officer
A1: Case | B1: Type | C1: Area | D1: What to test | E1: Steps | F1: Expected | G1: Permission | H1: Result | I1: Tester | J1: Date | K1: Notes
A2: occ_health_officer:sign-in | B2: Sign in | C2: Sign in | D2: Sign in as Occupational Health Officer | E2: app.medbrains.in → hospital code AMH → username test_occ_health_officer and the password from your test-accounts file. | F2: You are signed in; the header shows 'TEST - Occupational Health Officer'; you land on a page you can use (not an error). | H2: Not run
A3: occ_health_officer:see:/dashboard | B3: Should see | C3: Core | D3: Open Dashboard | E3: Menu → Core → Dashboard (/dashboard) | F3: The screen opens with no 'access denied' or error message. Lists load; an empty list says so. Buttons to add or change things appear only where this role should do that. | G3: dashboard.view | H3: Not run
A4: occ_health_officer:see:/approvals | B4: Should see | C4: Core | D4: Open Approvals | E4: Menu → Core → Approvals (/approvals) | F4: The screen opens with no 'access denied' or error message. Lists load; an empty list says so. Buttons to add or change things appear only where this role should do that. | H4: Not run
A5: occ_health_officer:see:/health-pulse | B5: Should see | C5: Core | D5: Open Health Pulse | E5: Menu → Core → Health Pulse (/health-pulse) | F5: The screen opens with no 'access denied' or error message. Lists load; an empty list says so. Buttons to add or change things appear only where this role should do that. | G5: dashboard.view | H5: Not run
A6: occ_health_officer:see:/occupational-health | B6: Should see | C6: Specialty | D6: Open Occupational Health | E6: Menu → Specialty → Occupational Health (/occupational-health) | F6: The screen opens with no 'access denied' or error message. Lists load; an empty list says so. Buttons to add or change things appear only where this role should do that. | G6: occ_health.screenings.list | H6: Not run
A7: occ_health_officer:menu | B7: Must not see | C7: Menu | D7: Menu shows only this role's screens | E7: Look through every menu group. | F7: These must NOT be in the menu: Token Board, Token Console, Patients, OPD Queue, Appointments, Telemedicine, Doctor Sign-offs, Emergency, Order Sets, Chronic Care, Home healthcare, Home visits, Lab, Radiology, Ward Stock, Pharmacy, Pharmacy Finance, Fulfilment Queue, Home Deliveries, Collection Counter, Blood Bank, IPD, Care View, Case sheet review, ICU, Nurse Activities, Operation Theatre, Diet & Kitchen, Bedside Portal, Billing, Insurance & TPA, Procurement, Indent & Store, Materials, Payroll, Front Office, Smart Scheduling, Command Center, Communications, Camp Management, Ambulance, Housekeeping, CSSD, Facilities Management, Biomedical Engineering, Security, HR & Staffing, Learning (LMS), Medical Records, Clinical Knowledge, Directory, Hospital groups, Inter-hospital transfers, Inter-hospital stock, Marketing, Health packages, Testimonials, Micro-site settings, Quality, Infection Control, Consent Management, Regulatory Compliance, Analytics & Dashboards, Reports Center, Audit Trail, Utilization Review, Case Management, Ophthalmology, Dental, Cath Lab, Endoscopy, Psychiatry, Physical Medicine, Palliative Care, Maternity, Other Specialties, Clinical trials, Long-term care, Users, Doctors, Roles & Permissions, Access Groups, Single Sign-On, Access Requests, NABH Indicators, Setup Center, Onboarding workbook, Settings, Document Templates, Built-in Pipelines, Forms, Test cycles, API keys, Webhooks, Doctor Schedules, Documents & Printing, Retrospective Entry, Device Integration, Paired Devices, Queues, Message Simulator. | H7: Not run
A8: occ_health_officer:url:/admin/users | B8: Must not see | C8: Administration | D8: Typing the address of Users | E8: Type app.medbrains.in/admin/users into the address bar. | F8: You get an 'access denied' page or are sent back — none of that screen's data is shown, even briefly. | G8: admin.users.list | H8: Not run
A9: occ_health_officer:url:/audit | B9: Must not see | C9: Compliance | D9: Typing the address of Audit Trail | E9: Type app.medbrains.in/audit into the address bar. | F9: You get an 'access denied' page or are sent back — none of that screen's data is shown, even briefly. | G9: audit.log.view | H9: Not run
A10: occ_health_officer:url:/billing | B10: Must not see | C10: Finance | D10: Typing the address of Billing | E10: Type app.medbrains.in/billing into the address bar. | F10: You get an 'access denied' page or are sent back — none of that screen's data is shown, even briefly. | G10: billing.invoices.list | H10: Not run
A11: occ_health_officer:url:/mrd | B11: Must not see | C11: Operations | D11: Typing the address of Medical Records | E11: Type app.medbrains.in/mrd into the address bar. | F11: You get an 'access denied' page or are sent back — none of that screen's data is shown, even briefly. | H11: Not run
A12: occ_health_officer:wf:employee-health-check | B12: Workflow | C12: Occupational Health | D12: Employee health check | E12: Occupational Health → record a staff fitness check. | F12: It is saved to that staff member's occupational record. | H12: Not run

Sheet Utilization Reviewer
A1: Case | B1: Type | C1: Area | D1: What to test | E1: Steps | F1: Expected | G1: Permission | H1: Result | I1: Tester | J1: Date | K1: Notes
A2: utilization_reviewer:sign-in | B2: Sign in | C2: Sign in | D2: Sign in as Utilization Reviewer | E2: app.medbrains.in → hospital code AMH → username test_utilization_reviewer and the password from your test-accounts file. | F2: You are signed in; the header shows 'TEST - Utilization Reviewer'; you land on a page you can use (not an error). | H2: Not run
A3: utilization_reviewer:see:/dashboard | B3: Should see | C3: Core | D3: Open Dashboard | E3: Menu → Core → Dashboard (/dashboard) | F3: The screen opens with no 'access denied' or error message. Lists load; an empty list says so. Buttons to add or change things appear only where this role should do that. | G3: dashboard.view | H3: Not run
A4: utilization_reviewer:see:/approvals | B4: Should see | C4: Core | D4: Open Approvals | E4: Menu → Core → Approvals (/approvals) | F4: The screen opens with no 'access denied' or error message. Lists load; an empty list says so. Buttons to add or change things appear only where this role should do that. | H4: Not run
A5: utilization_reviewer:see:/health-pulse | B5: Should see | C5: Core | D5: Open Health Pulse | E5: Menu → Core → Health Pulse (/health-pulse) | F5: The screen opens with no 'access denied' or error message. Lists load; an empty list says so. Buttons to add or change things appear only where this role should do that. | G5: dashboard.view | H5: Not run
A6: utilization_reviewer:see:/utilization-review | B6: Should see | C6: Compliance | D6: Open Utilization Review | E6: Menu → Compliance → Utilization Review (/utilization-review) | F6: The screen opens with no 'access denied' or error message. Lists load; an empty list says so. Buttons to add or change things appear only where this role should do that. | G6: ur.reviews.list | H6: Not run
A7: utilization_reviewer:menu | B7: Must not see | C7: Menu | D7: Menu shows only this role's screens | E7: Look through every menu group. | F7: These must NOT be in the menu: Token Board, Token Console, Patients, OPD Queue, Appointments, Telemedicine, Doctor Sign-offs, Emergency, Order Sets, Chronic Care, Home healthcare, Home visits, Lab, Radiology, Ward Stock, Pharmacy, Pharmacy Finance, Fulfilment Queue, Home Deliveries, Collection Counter, Blood Bank, IPD, Care View, Case sheet review, ICU, Nurse Activities, Operation Theatre, Diet & Kitchen, Bedside Portal, Billing, Insurance & TPA, Procurement, Indent & Store, Materials, Payroll, Front Office, Smart Scheduling, Command Center, Communications, Camp Management, Ambulance, Housekeeping, CSSD, Facilities Management, Biomedical Engineering, Security, HR & Staffing, Learning (LMS), Medical Records, Clinical Knowledge, Directory, Hospital groups, Inter-hospital transfers, Inter-hospital stock, Marketing, Health packages, Testimonials, Micro-site settings, Quality, Infection Control, Consent Management, Regulatory Compliance, Analytics & Dashboards, Reports Center, Audit Trail, Case Management, Ophthalmology, Dental, Cath Lab, Endoscopy, Psychiatry, Physical Medicine, Palliative Care, Maternity, Other Specialties, Clinical trials, Long-term care, Occupational Health, Users, Doctors, Roles & Permissions, Access Groups, Single Sign-On, Access Requests, NABH Indicators, Setup Center, Onboarding workbook, Settings, Document Templates, Built-in Pipelines, Forms, Test cycles, API keys, Webhooks, Doctor Schedules, Documents & Printing, Retrospective Entry, Device Integration, Paired Devices, Queues, Message Simulator. | H7: Not run
A8: utilization_reviewer:url:/admin/users | B8: Must not see | C8: Administration | D8: Typing the address of Users | E8: Type app.medbrains.in/admin/users into the address bar. | F8: You get an 'access denied' page or are sent back — none of that screen's data is shown, even briefly. | G8: admin.users.list | H8: Not run
A9: utilization_reviewer:url:/audit | B9: Must not see | C9: Compliance | D9: Typing the address of Audit Trail | E9: Type app.medbrains.in/audit into the address bar. | F9: You get an 'access denied' page or are sent back — none of that screen's data is shown, even briefly. | G9: audit.log.view | H9: Not run
A10: utilization_reviewer:url:/billing | B10: Must not see | C10: Finance | D10: Typing the address of Billing | E10: Type app.medbrains.in/billing into the address bar. | F10: You get an 'access denied' page or are sent back — none of that screen's data is shown, even briefly. | G10: billing.invoices.list | H10: Not run
A11: utilization_reviewer:url:/mrd | B11: Must not see | C11: Operations | D11: Typing the address of Medical Records | E11: Type app.medbrains.in/mrd into the address bar. | F11: You get an 'access denied' page or are sent back — none of that screen's data is shown, even briefly. | H11: Not run
A12: utilization_reviewer:wf:review-a-long-stay | B12: Workflow | C12: Utilization Review | D12: Review a long stay | E12: Utilization Review → open a review → record the decision. | F12: The decision is saved with your name. | H12: Not run

Sheet Case Manager
A1: Case | B1: Type | C1: Area | D1: What to test | E1: Steps | F1: Expected | G1: Permission | H1: Result | I1: Tester | J1: Date | K1: Notes
A2: case_manager:sign-in | B2: Sign in | C2: Sign in | D2: Sign in as Case Manager | E2: app.medbrains.in → hospital code AMH → username test_case_manager and the password from your test-accounts file. | F2: You are signed in; the header shows 'TEST - Case Manager'; you land on a page you can use (not an error). | H2: Not run
A3: case_manager:see:/dashboard | B3: Should see | C3: Core | D3: Open Dashboard | E3: Menu → Core → Dashboard (/dashboard) | F3: The screen opens with no 'access denied' or error message. Lists load; an empty list says so. Buttons to add or change things appear only where this role should do that. | G3: dashboard.view | H3: Not run
A4: case_manager:see:/approvals | B4: Should see | C4: Core | D4: Open Approvals | E4: Menu → Core → Approvals (/approvals) | F4: The screen opens with no 'access denied' or error message. Lists load; an empty list says so. Buttons to add or change things appear only where this role should do that. | H4: Not run
A5: case_manager:see:/health-pulse | B5: Should see | C5: Core | D5: Open Health Pulse | E5: Menu → Core → Health Pulse (/health-pulse) | F5: The screen opens with no 'access denied' or error message. Lists load; an empty list says so. Buttons to add or change things appear only where this role should do that. | G5: dashboard.view | H5: Not run
A6: case_manager:see:/case-management | B6: Should see | C6: Compliance | D6: Open Case Management | E6: Menu → Compliance → Case Management (/case-management) | F6: The screen opens with no 'access denied' or error message. Lists load; an empty list says so. Buttons to add or change things appear only where this role should do that. | G6: case_mgmt.assignments.list | H6: Not run
A7: case_manager:menu | B7: Must not see | C7: Menu | D7: Menu shows only this role's screens | E7: Look through every menu group. | F7: These must NOT be in the menu: Token Board, Token Console, Patients, OPD Queue, Appointments, Telemedicine, Doctor Sign-offs, Emergency, Order Sets, Chronic Care, Home healthcare, Home visits, Lab, Radiology, Ward Stock, Pharmacy, Pharmacy Finance, Fulfilment Queue, Home Deliveries, Collection Counter, Blood Bank, IPD, Care View, Case sheet review, ICU, Nurse Activities, Operation Theatre, Diet & Kitchen, Bedside Portal, Billing, Insurance & TPA, Procurement, Indent & Store, Materials, Payroll, Front Office, Smart Scheduling, Command Center, Communications, Camp Management, Ambulance, Housekeeping, CSSD, Facilities Management, Biomedical Engineering, Security, HR & Staffing, Learning (LMS), Medical Records, Clinical Knowledge, Directory, Hospital groups, Inter-hospital transfers, Inter-hospital stock, Marketing, Health packages, Testimonials, Micro-site settings, Quality, Infection Control, Consent Management, Regulatory Compliance, Analytics & Dashboards, Reports Center, Audit Trail, Utilization Review, Ophthalmology, Dental, Cath Lab, Endoscopy, Psychiatry, Physical Medicine, Palliative Care, Maternity, Other Specialties, Clinical trials, Long-term care, Occupational Health, Users, Doctors, Roles & Permissions, Access Groups, Single Sign-On, Access Requests, NABH Indicators, Setup Center, Onboarding workbook, Settings, Document Templates, Built-in Pipelines, Forms, Test cycles, API keys, Webhooks, Doctor Schedules, Documents & Printing, Retrospective Entry, Device Integration, Paired Devices, Queues, Message Simulator. | H7: Not run
A8: case_manager:url:/admin/users | B8: Must not see | C8: Administration | D8: Typing the address of Users | E8: Type app.medbrains.in/admin/users into the address bar. | F8: You get an 'access denied' page or are sent back — none of that screen's data is shown, even briefly. | G8: admin.users.list | H8: Not run
A9: case_manager:url:/audit | B9: Must not see | C9: Compliance | D9: Typing the address of Audit Trail | E9: Type app.medbrains.in/audit into the address bar. | F9: You get an 'access denied' page or are sent back — none of that screen's data is shown, even briefly. | G9: audit.log.view | H9: Not run
A10: case_manager:url:/billing | B10: Must not see | C10: Finance | D10: Typing the address of Billing | E10: Type app.medbrains.in/billing into the address bar. | F10: You get an 'access denied' page or are sent back — none of that screen's data is shown, even briefly. | G10: billing.invoices.list | H10: Not run
A11: case_manager:url:/mrd | B11: Must not see | C11: Operations | D11: Typing the address of Medical Records | E11: Type app.medbrains.in/mrd into the address bar. | F11: You get an 'access denied' page or are sent back — none of that screen's data is shown, even briefly. | H11: Not run
A12: case_manager:wf:assign-a-case | B12: Workflow | C12: Case Management | D12: Assign a case | E12: Case Management → assign an admitted patient to yourself → add a note. | F12: The assignment and note are listed. | H12: Not run

Sheet Scheduling Admin
A1: Case | B1: Type | C1: Area | D1: What to test | E1: Steps | F1: Expected | G1: Permission | H1: Result | I1: Tester | J1: Date | K1: Notes
A2: scheduling_admin:sign-in | B2: Sign in | C2: Sign in | D2: Sign in as Scheduling Admin | E2: app.medbrains.in → hospital code AMH → username test_scheduling_admin and the password from your test-accounts file. | F2: You are signed in; the header shows 'TEST - Scheduling Admin'; you land on a page you can use (not an error). | H2: Not run
A3: scheduling_admin:see:/dashboard | B3: Should see | C3: Core | D3: Open Dashboard | E3: Menu → Core → Dashboard (/dashboard) | F3: The screen opens with no 'access denied' or error message. Lists load; an empty list says so. Buttons to add or change things appear only where this role should do that. | G3: dashboard.view | H3: Not run
A4: scheduling_admin:see:/approvals | B4: Should see | C4: Core | D4: Open Approvals | E4: Menu → Core → Approvals (/approvals) | F4: The screen opens with no 'access denied' or error message. Lists load; an empty list says so. Buttons to add or change things appear only where this role should do that. | H4: Not run
A5: scheduling_admin:see:/health-pulse | B5: Should see | C5: Core | D5: Open Health Pulse | E5: Menu → Core → Health Pulse (/health-pulse) | F5: The screen opens with no 'access denied' or error message. Lists load; an empty list says so. Buttons to add or change things appear only where this role should do that. | G5: dashboard.view | H5: Not run
A6: scheduling_admin:see:/scheduling | B6: Should see | C6: Operations | D6: Open Smart Scheduling | E6: Menu → Operations → Smart Scheduling (/scheduling) | F6: The screen opens with no 'access denied' or error message. Lists load; an empty list says so. Buttons to add or change things appear only where this role should do that. | G6: scheduling.predictions.list | H6: Not run
A7: scheduling_admin:see:/reports | B7: Should see | C7: Compliance | D7: Open Reports Center | E7: Menu → Compliance → Reports Center (/reports) | F7: The screen opens with no 'access denied' or error message. Lists load; an empty list says so. Buttons to add or change things appear only where this role should do that. | G7: analytics.view, billing.reports.view, quality.indicators.list… | H7: Not run
A8: scheduling_admin:see:/admin/doctor-schedules | B8: Should see | C8: Administration | D8: Open Doctor Schedules | E8: Menu → Administration → Admin → Doctor Schedules (/admin/doctor-schedules) | F8: The screen opens with no 'access denied' or error message. Lists load; an empty list says so. Buttons to add or change things appear only where this role should do that. | G8: opd.schedule.list | H8: Not run
A9: scheduling_admin:menu | B9: Must not see | C9: Menu | D9: Menu shows only this role's screens | E9: Look through every menu group. | F9: These must NOT be in the menu: Token Board, Token Console, Patients, OPD Queue, Appointments, Telemedicine, Doctor Sign-offs, Emergency, Order Sets, Chronic Care, Home healthcare, Home visits, Lab, Radiology, Ward Stock, Pharmacy, Pharmacy Finance, Fulfilment Queue, Home Deliveries, Collection Counter, Blood Bank, IPD, Care View, Case sheet review, ICU, Nurse Activities, Operation Theatre, Diet & Kitchen, Bedside Portal, Billing, Insurance & TPA, Procurement, Indent & Store, Materials, Payroll, Front Office, Command Center, Communications, Camp Management, Ambulance, Housekeeping, CSSD, Facilities Management, Biomedical Engineering, Security, HR & Staffing, Learning (LMS), Medical Records, Clinical Knowledge, Directory, Hospital groups, Inter-hospital transfers, Inter-hospital stock, Marketing, Health packages, Testimonials, Micro-site settings, Quality, Infection Control, Consent Management, Regulatory Compliance, Analytics & Dashboards, Audit Trail, Utilization Review, Case Management, Ophthalmology, Dental, Cath Lab, Endoscopy, Psychiatry, Physical Medicine, Palliative Care, Maternity, Other Specialties, Clinical trials, Long-term care, Occupational Health, Users, Doctors, Roles & Permissions, Access Groups, Single Sign-On, Access Requests, NABH Indicators, Setup Center, Onboarding workbook, Settings, Document Templates, Built-in Pipelines, Forms, Test cycles, API keys, Webhooks, Documents & Printing, Retrospective Entry, Device Integration, Paired Devices, Queues, Message Simulator. | H9: Not run
A10: scheduling_admin:url:/admin/users | B10: Must not see | C10: Administration | D10: Typing the address of Users | E10: Type app.medbrains.in/admin/users into the address bar. | F10: You get an 'access denied' page or are sent back — none of that screen's data is shown, even briefly. | G10: admin.users.list | H10: Not run
A11: scheduling_admin:url:/audit | B11: Must not see | C11: Compliance | D11: Typing the address of Audit Trail | E11: Type app.medbrains.in/audit into the address bar. | F11: You get an 'access denied' page or are sent back — none of that screen's data is shown, even briefly. | G11: audit.log.view | H11: Not run
A12: scheduling_admin:url:/billing | B12: Must not see | C12: Finance | D12: Typing the address of Billing | E12: Type app.medbrains.in/billing into the address bar. | F12: You get an 'access denied' page or are sent back — none of that screen's data is shown, even briefly. | G12: billing.invoices.list | H12: Not run
A13: scheduling_admin:url:/mrd | B13: Must not see | C13: Operations | D13: Typing the address of Medical Records | E13: Type app.medbrains.in/mrd into the address bar. | F13: You get an 'access denied' page or are sent back — none of that screen's data is shown, even briefly. | H13: Not run
A14: scheduling_admin:wf:set-a-doctor-s-opd-schedule | B14: Workflow | C14: Smart Scheduling | D14: Set a doctor's OPD schedule | E14: Set clinic days and slot length for a doctor. | F14: Appointments can be booked only in those slots. | H14: Not run

Sheet MRD Officer
A1: Case | B1: Type | C1: Area | D1: What to test | E1: Steps | F1: Expected | G1: Permission | H1: Result | I1: Tester | J1: Date | K1: Notes
A2: mrd_officer:sign-in | B2: Sign in | C2: Sign in | D2: Sign in as MRD Officer | E2: app.medbrains.in → hospital code AMH → username test_mrd_officer and the password from your test-accounts file. | F2: You are signed in; the header shows 'TEST - MRD Officer'; you land on a page you can use (not an error). | H2: Not run
A3: mrd_officer:see:/dashboard | B3: Should see | C3: Core | D3: Open Dashboard | E3: Menu → Core → Dashboard (/dashboard) | F3: The screen opens with no 'access denied' or error message. Lists load; an empty list says so. Buttons to add or change things appear only where this role should do that. | G3: dashboard.view | H3: Not run
A4: mrd_officer:see:/approvals | B4: Should see | C4: Core | D4: Open Approvals | E4: Menu → Core → Approvals (/approvals) | F4: The screen opens with no 'access denied' or error message. Lists load; an empty list says so. Buttons to add or change things appear only where this role should do that. | H4: Not run
A5: mrd_officer:see:/health-pulse | B5: Should see | C5: Core | D5: Open Health Pulse | E5: Menu → Core → Health Pulse (/health-pulse) | F5: The screen opens with no 'access denied' or error message. Lists load; an empty list says so. Buttons to add or change things appear only where this role should do that. | G5: dashboard.view | H5: Not run
A6: mrd_officer:see:/patients | B6: Should see | C6: Clinical | D6: Open Patients | E6: Menu → Clinical → Patients (/patients) | F6: The screen opens with no 'access denied' or error message. Lists load; an empty list says so. Buttons to add or change things appear only where this role should do that. | G6: patients.list | H6: Not run
A7: mrd_officer:see:/opd | B7: Should see | C7: Clinical | D7: Open OPD Queue | E7: Menu → Clinical → OPD Queue (/opd) | F7: The screen opens with no 'access denied' or error message. Lists load; an empty list says so. Buttons to add or change things appear only where this role should do that. | G7: opd.queue.list | H7: Not run
A8: mrd_officer:see:/telemedicine | B8: Should see | C8: Clinical | D8: Open Telemedicine | E8: Menu → Clinical → Telemedicine (/telemedicine) | F8: The screen opens with no 'access denied' or error message. Lists load; an empty list says so. Buttons to add or change things appear only where this role should do that. | G8: opd.queue.view | H8: Not run
A9: mrd_officer:see:/ipd | B9: Should see | C9: Inpatient | D9: Open IPD | E9: Menu → Inpatient → IPD (/ipd) | F9: The screen opens with no 'access denied' or error message. Lists load; an empty list says so. Buttons to add or change things appear only where this role should do that. | G9: ipd.admissions.list | H9: Not run
A10: mrd_officer:see:/case-sheet-review | B10: Should see | C10: Inpatient | D10: Open Case sheet review | E10: Menu → Inpatient → Case sheet review (/case-sheet-review) | F10: The screen opens with no 'access denied' or error message. Lists load; an empty list says so. Buttons to add or change things appear only where this role should do that. | G10: mrd.case_sheets.view | H10: Not run
A11: mrd_officer:see:/mrd | B11: Should see | C11: Operations | D11: Open Medical Records | E11: Menu → Operations → Medical Records (/mrd) | F11: The screen opens with no 'access denied' or error message. Lists load; an empty list says so. Buttons to add or change things appear only where this role should do that. | G11: mrd.records.list, mrd.records.manage, mrd.case_sheets.view… | H11: Not run
A12: mrd_officer:menu | B12: Must not see | C12: Menu | D12: Menu shows only this role's screens | E12: Look through every menu group. | F12: These must NOT be in the menu: Token Board, Token Console, Appointments, Doctor Sign-offs, Emergency, Order Sets, Chronic Care, Home healthcare, Home visits, Lab, Radiology, Ward Stock, Pharmacy, Pharmacy Finance, Fulfilment Queue, Home Deliveries, Collection Counter, Blood Bank, Care View, ICU, Nurse Activities, Operation Theatre, Diet & Kitchen, Bedside Portal, Billing, Insurance & TPA, Procurement, Indent & Store, Materials, Payroll, Front Office, Smart Scheduling, Command Center, Communications, Camp Management, Ambulance, Housekeeping, CSSD, Facilities Management, Biomedical Engineering, Security, HR & Staffing, Learning (LMS), Clinical Knowledge, Directory, Hospital groups, Inter-hospital transfers, Inter-hospital stock, Marketing, Health packages, Testimonials, Micro-site settings, Quality, Infection Control, Consent Management, Regulatory Compliance, Analytics & Dashboards, Reports Center, Audit Trail, Utilization Review, Case Management, Ophthalmology, Dental, Cath Lab, Endoscopy, Psychiatry, Physical Medicine, Palliative Care, Maternity, Other Specialties, Clinical trials, Long-term care, Occupational Health, Users, Doctors, Roles & Permissions, Access Groups, Single Sign-On, Access Requests, NABH Indicators, Setup Center, Onboarding workbook, Settings, Document Templates, Built-in Pipelines, Forms, Test cycles, API keys, Webhooks, Doctor Schedules, Documents & Printing, Retrospective Entry, Device Integration, Paired Devices, Queues, Message Simulator. | H12: Not run
A13: mrd_officer:url:/admin/users | B13: Must not see | C13: Administration | D13: Typing the address of Users | E13: Type app.medbrains.in/admin/users into the address bar. | F13: You get an 'access denied' page or are sent back — none of that screen's data is shown, even briefly. | G13: admin.users.list | H13: Not run
A14: mrd_officer:url:/audit | B14: Must not see | C14: Compliance | D14: Typing the address of Audit Trail | E14: Type app.medbrains.in/audit into the address bar. | F14: You get an 'access denied' page or are sent back — none of that screen's data is shown, even briefly. | G14: audit.log.view | H14: Not run
A15: mrd_officer:url:/billing | B15: Must not see | C15: Finance | D15: Typing the address of Billing | E15: Type app.medbrains.in/billing into the address bar. | F15: You get an 'access denied' page or are sent back — none of that screen's data is shown, even briefly. | G15: billing.invoices.list | H15: Not run
A16: mrd_officer:url:/pharmacy | B16: Must not see | C16: Diagnostics | D16: Typing the address of Pharmacy | E16: Type app.medbrains.in/pharmacy into the address bar. | F16: You get an 'access denied' page or are sent back — none of that screen's data is shown, even briefly. | G16: pharmacy.prescriptions.list | H16: Not run
A17: mrd_officer:wf:find-and-review-a-case-sheet | B17: Workflow | C17: Medical Records | D17: Find and review a case sheet | E17: Medical Records → search a discharged patient → open the case sheet. | F17: The full record opens read-only; printed documents are filed in it. | H17: Not run

Sheet Canteen Staff
A1: Case | B1: Type | C1: Area | D1: What to test | E1: Steps | F1: Expected | G1: Permission | H1: Result | I1: Tester | J1: Date | K1: Notes
A2: canteen_staff:sign-in | B2: Sign in | C2: Sign in | D2: Sign in as Canteen Staff | E2: app.medbrains.in → hospital code AMH → username test_canteen_staff and the password from your test-accounts file. | F2: You are signed in; the header shows 'TEST - Canteen Staff'; you land on a page you can use (not an error). | H2: Not run
A3: canteen_staff:see:/dashboard | B3: Should see | C3: Core | D3: Open Dashboard | E3: Menu → Core → Dashboard (/dashboard) | F3: The screen opens with no 'access denied' or error message. Lists load; an empty list says so. Buttons to add or change things appear only where this role should do that. | G3: dashboard.view | H3: Not run
A4: canteen_staff:see:/approvals | B4: Should see | C4: Core | D4: Open Approvals | E4: Menu → Core → Approvals (/approvals) | F4: The screen opens with no 'access denied' or error message. Lists load; an empty list says so. Buttons to add or change things appear only where this role should do that. | H4: Not run
A5: canteen_staff:see:/health-pulse | B5: Should see | C5: Core | D5: Open Health Pulse | E5: Menu → Core → Health Pulse (/health-pulse) | F5: The screen opens with no 'access denied' or error message. Lists load; an empty list says so. Buttons to add or change things appear only where this role should do that. | G5: dashboard.view | H5: Not run
A6: canteen_staff:see:/diet-kitchen | B6: Should see | C6: Inpatient | D6: Open Diet & Kitchen | E6: Menu → Inpatient → Diet & Kitchen (/diet-kitchen) | F6: The screen opens with no 'access denied' or error message. Lists load; an empty list says so. Buttons to add or change things appear only where this role should do that. | G6: diet.orders.list | H6: Not run
A7: canteen_staff:menu | B7: Must not see | C7: Menu | D7: Menu shows only this role's screens | E7: Look through every menu group. | F7: These must NOT be in the menu: Token Board, Token Console, Patients, OPD Queue, Appointments, Telemedicine, Doctor Sign-offs, Emergency, Order Sets, Chronic Care, Home healthcare, Home visits, Lab, Radiology, Ward Stock, Pharmacy, Pharmacy Finance, Fulfilment Queue, Home Deliveries, Collection Counter, Blood Bank, IPD, Care View, Case sheet review, ICU, Nurse Activities, Operation Theatre, Bedside Portal, Billing, Insurance & TPA, Procurement, Indent & Store, Materials, Payroll, Front Office, Smart Scheduling, Command Center, Communications, Camp Management, Ambulance, Housekeeping, CSSD, Facilities Management, Biomedical Engineering, Security, HR & Staffing, Learning (LMS), Medical Records, Clinical Knowledge, Directory, Hospital groups, Inter-hospital transfers, Inter-hospital stock, Marketing, Health packages, Testimonials, Micro-site settings, Quality, Infection Control, Consent Management, Regulatory Compliance, Analytics & Dashboards, Reports Center, Audit Trail, Utilization Review, Case Management, Ophthalmology, Dental, Cath Lab, Endoscopy, Psychiatry, Physical Medicine, Palliative Care, Maternity, Other Specialties, Clinical trials, Long-term care, Occupational Health, Users, Doctors, Roles & Permissions, Access Groups, Single Sign-On, Access Requests, NABH Indicators, Setup Center, Onboarding workbook, Settings, Document Templates, Built-in Pipelines, Forms, Test cycles, API keys, Webhooks, Doctor Schedules, Documents & Printing, Retrospective Entry, Device Integration, Paired Devices, Queues, Message Simulator. | H7: Not run
A8: canteen_staff:url:/admin/users | B8: Must not see | C8: Administration | D8: Typing the address of Users | E8: Type app.medbrains.in/admin/users into the address bar. | F8: You get an 'access denied' page or are sent back — none of that screen's data is shown, even briefly. | G8: admin.users.list | H8: Not run
A9: canteen_staff:url:/audit | B9: Must not see | C9: Compliance | D9: Typing the address of Audit Trail | E9: Type app.medbrains.in/audit into the address bar. | F9: You get an 'access denied' page or are sent back — none of that screen's data is shown, even briefly. | G9: audit.log.view | H9: Not run
A10: canteen_staff:url:/billing | B10: Must not see | C10: Finance | D10: Typing the address of Billing | E10: Type app.medbrains.in/billing into the address bar. | F10: You get an 'access denied' page or are sent back — none of that screen's data is shown, even briefly. | G10: billing.invoices.list | H10: Not run
A11: canteen_staff:url:/mrd | B11: Must not see | C11: Operations | D11: Typing the address of Medical Records | E11: Type app.medbrains.in/mrd into the address bar. | F11: You get an 'access denied' page or are sent back — none of that screen's data is shown, even briefly. | H11: Not run
A12: canteen_staff:wf:kitchen-meal-list | B12: Workflow | C12: Diet & Kitchen | D12: Kitchen meal list | E12: Open the kitchen / meal list for today. | F12: Meals per ward and diet type are listed; no patient clinical notes are visible. | H12: Not run

Sheet Dietitian
A1: Case | B1: Type | C1: Area | D1: What to test | E1: Steps | F1: Expected | G1: Permission | H1: Result | I1: Tester | J1: Date | K1: Notes
A2: dietitian:sign-in | B2: Sign in | C2: Sign in | D2: Sign in as Dietitian | E2: app.medbrains.in → hospital code AMH → username test_dietitian and the password from your test-accounts file. | F2: You are signed in; the header shows 'TEST - Dietitian'; you land on a page you can use (not an error). | H2: Not run
A3: dietitian:see:/dashboard | B3: Should see | C3: Core | D3: Open Dashboard | E3: Menu → Core → Dashboard (/dashboard) | F3: The screen opens with no 'access denied' or error message. Lists load; an empty list says so. Buttons to add or change things appear only where this role should do that. | G3: dashboard.view | H3: Not run
A4: dietitian:see:/approvals | B4: Should see | C4: Core | D4: Open Approvals | E4: Menu → Core → Approvals (/approvals) | F4: The screen opens with no 'access denied' or error message. Lists load; an empty list says so. Buttons to add or change things appear only where this role should do that. | H4: Not run
A5: dietitian:see:/health-pulse | B5: Should see | C5: Core | D5: Open Health Pulse | E5: Menu → Core → Health Pulse (/health-pulse) | F5: The screen opens with no 'access denied' or error message. Lists load; an empty list says so. Buttons to add or change things appear only where this role should do that. | G5: dashboard.view | H5: Not run
A6: dietitian:see:/diet-kitchen | B6: Should see | C6: Inpatient | D6: Open Diet & Kitchen | E6: Menu → Inpatient → Diet & Kitchen (/diet-kitchen) | F6: The screen opens with no 'access denied' or error message. Lists load; an empty list says so. Buttons to add or change things appear only where this role should do that. | G6: diet.orders.list | H6: Not run
A7: dietitian:menu | B7: Must not see | C7: Menu | D7: Menu shows only this role's screens | E7: Look through every menu group. | F7: These must NOT be in the menu: Token Board, Token Console, Patients, OPD Queue, Appointments, Telemedicine, Doctor Sign-offs, Emergency, Order Sets, Chronic Care, Home healthcare, Home visits, Lab, Radiology, Ward Stock, Pharmacy, Pharmacy Finance, Fulfilment Queue, Home Deliveries, Collection Counter, Blood Bank, IPD, Care View, Case sheet review, ICU, Nurse Activities, Operation Theatre, Bedside Portal, Billing, Insurance & TPA, Procurement, Indent & Store, Materials, Payroll, Front Office, Smart Scheduling, Command Center, Communications, Camp Management, Ambulance, Housekeeping, CSSD, Facilities Management, Biomedical Engineering, Security, HR & Staffing, Learning (LMS), Medical Records, Clinical Knowledge, Directory, Hospital groups, Inter-hospital transfers, Inter-hospital stock, Marketing, Health packages, Testimonials, Micro-site settings, Quality, Infection Control, Consent Management, Regulatory Compliance, Analytics & Dashboards, Reports Center, Audit Trail, Utilization Review, Case Management, Ophthalmology, Dental, Cath Lab, Endoscopy, Psychiatry, Physical Medicine, Palliative Care, Maternity, Other Specialties, Clinical trials, Long-term care, Occupational Health, Users, Doctors, Roles & Permissions, Access Groups, Single Sign-On, Access Requests, NABH Indicators, Setup Center, Onboarding workbook, Settings, Document Templates, Built-in Pipelines, Forms, Test cycles, API keys, Webhooks, Doctor Schedules, Documents & Printing, Retrospective Entry, Device Integration, Paired Devices, Queues, Message Simulator. | H7: Not run
A8: dietitian:url:/admin/users | B8: Must not see | C8: Administration | D8: Typing the address of Users | E8: Type app.medbrains.in/admin/users into the address bar. | F8: You get an 'access denied' page or are sent back — none of that screen's data is shown, even briefly. | G8: admin.users.list | H8: Not run
A9: dietitian:url:/audit | B9: Must not see | C9: Compliance | D9: Typing the address of Audit Trail | E9: Type app.medbrains.in/audit into the address bar. | F9: You get an 'access denied' page or are sent back — none of that screen's data is shown, even briefly. | G9: audit.log.view | H9: Not run
A10: dietitian:url:/billing | B10: Must not see | C10: Finance | D10: Typing the address of Billing | E10: Type app.medbrains.in/billing into the address bar. | F10: You get an 'access denied' page or are sent back — none of that screen's data is shown, even briefly. | G10: billing.invoices.list | H10: Not run
A11: dietitian:url:/mrd | B11: Must not see | C11: Operations | D11: Typing the address of Medical Records | E11: Type app.medbrains.in/mrd into the address bar. | F11: You get an 'access denied' page or are sent back — none of that screen's data is shown, even briefly. | H11: Not run
A12: dietitian:wf:order-a-therapeutic-diet | B12: Workflow | C12: Diet & Kitchen | D12: Order a therapeutic diet | E12: Diet & Kitchen → an admitted patient → set a diabetic diet. | F12: The diet shows on the kitchen list for the next meal. | H12: Not run

Sheet Security Guard
A1: Case | B1: Type | C1: Area | D1: What to test | E1: Steps | F1: Expected | G1: Permission | H1: Result | I1: Tester | J1: Date | K1: Notes
A2: security_guard:sign-in | B2: Sign in | C2: Sign in | D2: Sign in as Security Guard | E2: app.medbrains.in → hospital code AMH → username test_security_guard and the password from your test-accounts file. | F2: You are signed in; the header shows 'TEST - Security Guard'; you land on a page you can use (not an error). | H2: Not run
A3: security_guard:see:/dashboard | B3: Should see | C3: Core | D3: Open Dashboard | E3: Menu → Core → Dashboard (/dashboard) | F3: The screen opens with no 'access denied' or error message. Lists load; an empty list says so. Buttons to add or change things appear only where this role should do that. | G3: dashboard.view | H3: Not run
A4: security_guard:see:/approvals | B4: Should see | C4: Core | D4: Open Approvals | E4: Menu → Core → Approvals (/approvals) | F4: The screen opens with no 'access denied' or error message. Lists load; an empty list says so. Buttons to add or change things appear only where this role should do that. | H4: Not run
A5: security_guard:see:/health-pulse | B5: Should see | C5: Core | D5: Open Health Pulse | E5: Menu → Core → Health Pulse (/health-pulse) | F5: The screen opens with no 'access denied' or error message. Lists load; an empty list says so. Buttons to add or change things appear only where this role should do that. | G5: dashboard.view | H5: Not run
A6: security_guard:see:/front-office | B6: Should see | C6: Operations | D6: Open Front Office | E6: Menu → Operations → Front Office (/front-office) | F6: The screen opens with no 'access denied' or error message. Lists load; an empty list says so. Buttons to add or change things appear only where this role should do that. | G6: front_office.visitors.list, front_office.visitors.create, front_office.visitors.manage… | H6: Not run
A7: security_guard:see:/security | B7: Should see | C7: Operations | D7: Open Security | E7: Menu → Operations → Security (/security) | F7: The screen opens with no 'access denied' or error message. Lists load; an empty list says so. Buttons to add or change things appear only where this role should do that. | G7: security.access.list | H7: Not run
A8: security_guard:menu | B8: Must not see | C8: Menu | D8: Menu shows only this role's screens | E8: Look through every menu group. | F8: These must NOT be in the menu: Token Board, Token Console, Patients, OPD Queue, Appointments, Telemedicine, Doctor Sign-offs, Emergency, Order Sets, Chronic Care, Home healthcare, Home visits, Lab, Radiology, Ward Stock, Pharmacy, Pharmacy Finance, Fulfilment Queue, Home Deliveries, Collection Counter, Blood Bank, IPD, Care View, Case sheet review, ICU, Nurse Activities, Operation Theatre, Diet & Kitchen, Bedside Portal, Billing, Insurance & TPA, Procurement, Indent & Store, Materials, Payroll, Smart Scheduling, Command Center, Communications, Camp Management, Ambulance, Housekeeping, CSSD, Facilities Management, Biomedical Engineering, HR & Staffing, Learning (LMS), Medical Records, Clinical Knowledge, Directory, Hospital groups, Inter-hospital transfers, Inter-hospital stock, Marketing, Health packages, Testimonials, Micro-site settings, Quality, Infection Control, Consent Management, Regulatory Compliance, Analytics & Dashboards, Reports Center, Audit Trail, Utilization Review, Case Management, Ophthalmology, Dental, Cath Lab, Endoscopy, Psychiatry, Physical Medicine, Palliative Care, Maternity, Other Specialties, Clinical trials, Long-term care, Occupational Health, Users, Doctors, Roles & Permissions, Access Groups, Single Sign-On, Access Requests, NABH Indicators, Setup Center, Onboarding workbook, Settings, Document Templates, Built-in Pipelines, Forms, Test cycles, API keys, Webhooks, Doctor Schedules, Documents & Printing, Retrospective Entry, Device Integration, Paired Devices, Queues, Message Simulator. | H8: Not run
A9: security_guard:url:/admin/users | B9: Must not see | C9: Administration | D9: Typing the address of Users | E9: Type app.medbrains.in/admin/users into the address bar. | F9: You get an 'access denied' page or are sent back — none of that screen's data is shown, even briefly. | G9: admin.users.list | H9: Not run
A10: security_guard:url:/audit | B10: Must not see | C10: Compliance | D10: Typing the address of Audit Trail | E10: Type app.medbrains.in/audit into the address bar. | F10: You get an 'access denied' page or are sent back — none of that screen's data is shown, even briefly. | G10: audit.log.view | H10: Not run
A11: security_guard:url:/billing | B11: Must not see | C11: Finance | D11: Typing the address of Billing | E11: Type app.medbrains.in/billing into the address bar. | F11: You get an 'access denied' page or are sent back — none of that screen's data is shown, even briefly. | G11: billing.invoices.list | H11: Not run
A12: security_guard:url:/mrd | B12: Must not see | C12: Operations | D12: Typing the address of Medical Records | E12: Type app.medbrains.in/mrd into the address bar. | F12: You get an 'access denied' page or are sent back — none of that screen's data is shown, even briefly. | H12: Not run
A13: security_guard:wf:record-an-access-event | B13: Workflow | C13: Security | D13: Record an access event | E13: Security → log an entry at a gate or restricted zone. | F13: It appears in the access log with time and zone. | H13: Not run

Sheet Biomedical Engineer
A1: Case | B1: Type | C1: Area | D1: What to test | E1: Steps | F1: Expected | G1: Permission | H1: Result | I1: Tester | J1: Date | K1: Notes
A2: biomed_engineer:sign-in | B2: Sign in | C2: Sign in | D2: Sign in as Biomedical Engineer | E2: app.medbrains.in → hospital code AMH → username test_biomed_engineer and the password from your test-accounts file. | F2: You are signed in; the header shows 'TEST - Biomedical Engineer'; you land on a page you can use (not an error). | H2: Not run
A3: biomed_engineer:see:/dashboard | B3: Should see | C3: Core | D3: Open Dashboard | E3: Menu → Core → Dashboard (/dashboard) | F3: The screen opens with no 'access denied' or error message. Lists load; an empty list says so. Buttons to add or change things appear only where this role should do that. | G3: dashboard.view | H3: Not run
A4: biomed_engineer:see:/approvals | B4: Should see | C4: Core | D4: Open Approvals | E4: Menu → Core → Approvals (/approvals) | F4: The screen opens with no 'access denied' or error message. Lists load; an empty list says so. Buttons to add or change things appear only where this role should do that. | H4: Not run
A5: biomed_engineer:see:/health-pulse | B5: Should see | C5: Core | D5: Open Health Pulse | E5: Menu → Core → Health Pulse (/health-pulse) | F5: The screen opens with no 'access denied' or error message. Lists load; an empty list says so. Buttons to add or change things appear only where this role should do that. | G5: dashboard.view | H5: Not run
A6: biomed_engineer:see:/materials | B6: Should see | C6: Finance | D6: Open Materials | E6: Menu → Finance → Materials (/materials) | F6: The screen opens with no 'access denied' or error message. Lists load; an empty list says so. Buttons to add or change things appear only where this role should do that. | G6: indent.list, assets.list, procurement.vendors.list… | H6: Not run
A7: biomed_engineer:see:/bme | B7: Should see | C7: Operations | D7: Open Biomedical Engineering | E7: Menu → Operations → Biomedical Engineering (/bme) | F7: The screen opens with no 'access denied' or error message. Lists load; an empty list says so. Buttons to add or change things appear only where this role should do that. | G7: bme.equipment.list | H7: Not run
A8: biomed_engineer:see:/admin/devices | B8: Should see | C8: Administration | D8: Open Device Integration | E8: Menu → Administration → Admin → Device Integration (/admin/devices) | F8: The screen opens with no 'access denied' or error message. Lists load; an empty list says so. Buttons to add or change things appear only where this role should do that. | G8: devices.list | H8: Not run
A9: biomed_engineer:see:/admin/paired-devices | B9: Should see | C9: Administration | D9: Open Paired Devices | E9: Menu → Administration → Admin → Paired Devices (/admin/paired-devices) | F9: The screen opens with no 'access denied' or error message. Lists load; an empty list says so. Buttons to add or change things appear only where this role should do that. | G9: devices.pairing.paired.list | H9: Not run
A10: biomed_engineer:menu | B10: Must not see | C10: Menu | D10: Menu shows only this role's screens | E10: Look through every menu group. | F10: These must NOT be in the menu: Token Board, Token Console, Patients, OPD Queue, Appointments, Telemedicine, Doctor Sign-offs, Emergency, Order Sets, Chronic Care, Home healthcare, Home visits, Lab, Radiology, Ward Stock, Pharmacy, Pharmacy Finance, Fulfilment Queue, Home Deliveries, Collection Counter, Blood Bank, IPD, Care View, Case sheet review, ICU, Nurse Activities, Operation Theatre, Diet & Kitchen, Bedside Portal, Billing, Insurance & TPA, Procurement, Indent & Store, Payroll, Front Office, Smart Scheduling, Command Center, Communications, Camp Management, Ambulance, Housekeeping, CSSD, Facilities Management, Security, HR & Staffing, Learning (LMS), Medical Records, Clinical Knowledge, Directory, Hospital groups, Inter-hospital transfers, Inter-hospital stock, Marketing, Health packages, Testimonials, Micro-site settings, Quality, Infection Control, Consent Management, Regulatory Compliance, Analytics & Dashboards, Reports Center, Audit Trail, Utilization Review, Case Management, Ophthalmology, Dental, Cath Lab, Endoscopy, Psychiatry, Physical Medicine, Palliative Care, Maternity, Other Specialties, Clinical trials, Long-term care, Occupational Health, Users, Doctors, Roles & Permissions, Access Groups, Single Sign-On, Access Requests, NABH Indicators, Setup Center, Onboarding workbook, Settings, Document Templates, Built-in Pipelines, Forms, Test cycles, API keys, Webhooks, Doctor Schedules, Documents & Printing, Retrospective Entry, Queues, Message Simulator. | H10: Not run
A11: biomed_engineer:url:/admin/users | B11: Must not see | C11: Administration | D11: Typing the address of Users | E11: Type app.medbrains.in/admin/users into the address bar. | F11: You get an 'access denied' page or are sent back — none of that screen's data is shown, even briefly. | G11: admin.users.list | H11: Not run
A12: biomed_engineer:url:/audit | B12: Must not see | C12: Compliance | D12: Typing the address of Audit Trail | E12: Type app.medbrains.in/audit into the address bar. | F12: You get an 'access denied' page or are sent back — none of that screen's data is shown, even briefly. | G12: audit.log.view | H12: Not run
A13: biomed_engineer:url:/billing | B13: Must not see | C13: Finance | D13: Typing the address of Billing | E13: Type app.medbrains.in/billing into the address bar. | F13: You get an 'access denied' page or are sent back — none of that screen's data is shown, even briefly. | G13: billing.invoices.list | H13: Not run
A14: biomed_engineer:url:/mrd | B14: Must not see | C14: Operations | D14: Typing the address of Medical Records | E14: Type app.medbrains.in/mrd into the address bar. | F14: You get an 'access denied' page or are sent back — none of that screen's data is shown, even briefly. | H14: Not run
A15: biomed_engineer:wf:calibration-due | B15: Workflow | C15: Biomedical Engineering | D15: Calibration due | E15: Biomedical Engineering → an equipment item → record calibration. | F15: The next due date updates; overdue equipment is flagged. | H15: Not run

Sheet Ambulance Driver
A1: Case | B1: Type | C1: Area | D1: What to test | E1: Steps | F1: Expected | G1: Permission | H1: Result | I1: Tester | J1: Date | K1: Notes
A2: ambulance_driver:sign-in | B2: Sign in | C2: Sign in | D2: Sign in as Ambulance Driver | E2: app.medbrains.in → hospital code AMH → username test_ambulance_driver and the password from your test-accounts file. | F2: You are signed in; the header shows 'TEST - Ambulance Driver'; you land on a page you can use (not an error). | H2: Not run
A3: ambulance_driver:see:/dashboard | B3: Should see | C3: Core | D3: Open Dashboard | E3: Menu → Core → Dashboard (/dashboard) | F3: The screen opens with no 'access denied' or error message. Lists load; an empty list says so. Buttons to add or change things appear only where this role should do that. | G3: dashboard.view | H3: Not run
A4: ambulance_driver:see:/approvals | B4: Should see | C4: Core | D4: Open Approvals | E4: Menu → Core → Approvals (/approvals) | F4: The screen opens with no 'access denied' or error message. Lists load; an empty list says so. Buttons to add or change things appear only where this role should do that. | H4: Not run
A5: ambulance_driver:see:/health-pulse | B5: Should see | C5: Core | D5: Open Health Pulse | E5: Menu → Core → Health Pulse (/health-pulse) | F5: The screen opens with no 'access denied' or error message. Lists load; an empty list says so. Buttons to add or change things appear only where this role should do that. | G5: dashboard.view | H5: Not run
A6: ambulance_driver:see:/ambulance | B6: Should see | C6: Operations | D6: Open Ambulance | E6: Menu → Operations → Ambulance (/ambulance) | F6: The screen opens with no 'access denied' or error message. Lists load; an empty list says so. Buttons to add or change things appear only where this role should do that. | G6: ambulance.fleet.list | H6: Not run
A7: ambulance_driver:menu | B7: Must not see | C7: Menu | D7: Menu shows only this role's screens | E7: Look through every menu group. | F7: These must NOT be in the menu: Token Board, Token Console, Patients, OPD Queue, Appointments, Telemedicine, Doctor Sign-offs, Emergency, Order Sets, Chronic Care, Home healthcare, Home visits, Lab, Radiology, Ward Stock, Pharmacy, Pharmacy Finance, Fulfilment Queue, Home Deliveries, Collection Counter, Blood Bank, IPD, Care View, Case sheet review, ICU, Nurse Activities, Operation Theatre, Diet & Kitchen, Bedside Portal, Billing, Insurance & TPA, Procurement, Indent & Store, Materials, Payroll, Front Office, Smart Scheduling, Command Center, Communications, Camp Management, Housekeeping, CSSD, Facilities Management, Biomedical Engineering, Security, HR & Staffing, Learning (LMS), Medical Records, Clinical Knowledge, Directory, Hospital groups, Inter-hospital transfers, Inter-hospital stock, Marketing, Health packages, Testimonials, Micro-site settings, Quality, Infection Control, Consent Management, Regulatory Compliance, Analytics & Dashboards, Reports Center, Audit Trail, Utilization Review, Case Management, Ophthalmology, Dental, Cath Lab, Endoscopy, Psychiatry, Physical Medicine, Palliative Care, Maternity, Other Specialties, Clinical trials, Long-term care, Occupational Health, Users, Doctors, Roles & Permissions, Access Groups, Single Sign-On, Access Requests, NABH Indicators, Setup Center, Onboarding workbook, Settings, Document Templates, Built-in Pipelines, Forms, Test cycles, API keys, Webhooks, Doctor Schedules, Documents & Printing, Retrospective Entry, Device Integration, Paired Devices, Queues, Message Simulator. | H7: Not run
A8: ambulance_driver:url:/admin/users | B8: Must not see | C8: Administration | D8: Typing the address of Users | E8: Type app.medbrains.in/admin/users into the address bar. | F8: You get an 'access denied' page or are sent back — none of that screen's data is shown, even briefly. | G8: admin.users.list | H8: Not run
A9: ambulance_driver:url:/audit | B9: Must not see | C9: Compliance | D9: Typing the address of Audit Trail | E9: Type app.medbrains.in/audit into the address bar. | F9: You get an 'access denied' page or are sent back — none of that screen's data is shown, even briefly. | G9: audit.log.view | H9: Not run
A10: ambulance_driver:url:/billing | B10: Must not see | C10: Finance | D10: Typing the address of Billing | E10: Type app.medbrains.in/billing into the address bar. | F10: You get an 'access denied' page or are sent back — none of that screen's data is shown, even briefly. | G10: billing.invoices.list | H10: Not run
A11: ambulance_driver:url:/mrd | B11: Must not see | C11: Operations | D11: Typing the address of Medical Records | E11: Type app.medbrains.in/mrd into the address bar. | F11: You get an 'access denied' page or are sent back — none of that screen's data is shown, even briefly. | H11: Not run
A12: ambulance_driver:wf:complete-a-trip | B12: Workflow | C12: Ambulance | D12: Complete a trip | E12: Ambulance → an assigned trip → start → reached → completed. | F12: Times are recorded for each stage. | H12: Not run

Sheet Radiology Technician
A1: Case | B1: Type | C1: Area | D1: What to test | E1: Steps | F1: Expected | G1: Permission | H1: Result | I1: Tester | J1: Date | K1: Notes
A2: radiology_tech:sign-in | B2: Sign in | C2: Sign in | D2: Sign in as Radiology Technician | E2: app.medbrains.in → hospital code AMH → username test_radiology_tech and the password from your test-accounts file. | F2: You are signed in; the header shows 'TEST - Radiology Technician'; you land on a page you can use (not an error). | H2: Not run
A3: radiology_tech:see:/dashboard | B3: Should see | C3: Core | D3: Open Dashboard | E3: Menu → Core → Dashboard (/dashboard) | F3: The screen opens with no 'access denied' or error message. Lists load; an empty list says so. Buttons to add or change things appear only where this role should do that. | G3: dashboard.view | H3: Not run
A4: radiology_tech:see:/approvals | B4: Should see | C4: Core | D4: Open Approvals | E4: Menu → Core → Approvals (/approvals) | F4: The screen opens with no 'access denied' or error message. Lists load; an empty list says so. Buttons to add or change things appear only where this role should do that. | H4: Not run
A5: radiology_tech:see:/health-pulse | B5: Should see | C5: Core | D5: Open Health Pulse | E5: Menu → Core → Health Pulse (/health-pulse) | F5: The screen opens with no 'access denied' or error message. Lists load; an empty list says so. Buttons to add or change things appear only where this role should do that. | G5: dashboard.view | H5: Not run
A6: radiology_tech:see:/radiology | B6: Should see | C6: Diagnostics | D6: Open Radiology | E6: Menu → Diagnostics → Radiology (/radiology) | F6: The screen opens with no 'access denied' or error message. Lists load; an empty list says so. Buttons to add or change things appear only where this role should do that. (Hidden if the hospital has this module switched off.) | G6: radiology.orders.list | H6: Not run
A7: radiology_tech:see:/reports | B7: Should see | C7: Compliance | D7: Open Reports Center | E7: Menu → Compliance → Reports Center (/reports) | F7: The screen opens with no 'access denied' or error message. Lists load; an empty list says so. Buttons to add or change things appear only where this role should do that. | G7: analytics.view, billing.reports.view, quality.indicators.list… | H7: Not run
A8: radiology_tech:menu | B8: Must not see | C8: Menu | D8: Menu shows only this role's screens | E8: Look through every menu group. | F8: These must NOT be in the menu: Token Board, Token Console, Patients, OPD Queue, Appointments, Telemedicine, Doctor Sign-offs, Emergency, Order Sets, Chronic Care, Home healthcare, Home visits, Lab, Ward Stock, Pharmacy, Pharmacy Finance, Fulfilment Queue, Home Deliveries, Collection Counter, Blood Bank, IPD, Care View, Case sheet review, ICU, Nurse Activities, Operation Theatre, Diet & Kitchen, Bedside Portal, Billing, Insurance & TPA, Procurement, Indent & Store, Materials, Payroll, Front Office, Smart Scheduling, Command Center, Communications, Camp Management, Ambulance, Housekeeping, CSSD, Facilities Management, Biomedical Engineering, Security, HR & Staffing, Learning (LMS), Medical Records, Clinical Knowledge, Directory, Hospital groups, Inter-hospital transfers, Inter-hospital stock, Marketing, Health packages, Testimonials, Micro-site settings, Quality, Infection Control, Consent Management, Regulatory Compliance, Analytics & Dashboards, Audit Trail, Utilization Review, Case Management, Ophthalmology, Dental, Cath Lab, Endoscopy, Psychiatry, Physical Medicine, Palliative Care, Maternity, Other Specialties, Clinical trials, Long-term care, Occupational Health, Users, Doctors, Roles & Permissions, Access Groups, Single Sign-On, Access Requests, NABH Indicators, Setup Center, Onboarding workbook, Settings, Document Templates, Built-in Pipelines, Forms, Test cycles, API keys, Webhooks, Doctor Schedules, Documents & Printing, Retrospective Entry, Device Integration, Paired Devices, Queues, Message Simulator. | H8: Not run
A9: radiology_tech:url:/admin/users | B9: Must not see | C9: Administration | D9: Typing the address of Users | E9: Type app.medbrains.in/admin/users into the address bar. | F9: You get an 'access denied' page or are sent back — none of that screen's data is shown, even briefly. | G9: admin.users.list | H9: Not run
A10: radiology_tech:url:/audit | B10: Must not see | C10: Compliance | D10: Typing the address of Audit Trail | E10: Type app.medbrains.in/audit into the address bar. | F10: You get an 'access denied' page or are sent back — none of that screen's data is shown, even briefly. | G10: audit.log.view | H10: Not run
A11: radiology_tech:url:/billing | B11: Must not see | C11: Finance | D11: Typing the address of Billing | E11: Type app.medbrains.in/billing into the address bar. | F11: You get an 'access denied' page or are sent back — none of that screen's data is shown, even briefly. | G11: billing.invoices.list | H11: Not run
A12: radiology_tech:url:/mrd | B12: Must not see | C12: Operations | D12: Typing the address of Medical Records | E12: Type app.medbrains.in/mrd into the address bar. | F12: You get an 'access denied' page or are sent back — none of that screen's data is shown, even briefly. | H12: Not run
A13: radiology_tech:wf:perform-an-ordered-exam | B13: Workflow | C13: Radiology | D13: Perform an ordered exam | E13: (As test_doctor, order a chest X-ray.) Radiology → worklist → the order → start → complete. | F13: The order moves through the worklist; with PACS connected the images link to the order. | H13: Not run

Sheet CSSD Technician
A1: Case | B1: Type | C1: Area | D1: What to test | E1: Steps | F1: Expected | G1: Permission | H1: Result | I1: Tester | J1: Date | K1: Notes
A2: cssd_technician:sign-in | B2: Sign in | C2: Sign in | D2: Sign in as CSSD Technician | E2: app.medbrains.in → hospital code AMH → username test_cssd_technician and the password from your test-accounts file. | F2: You are signed in; the header shows 'TEST - CSSD Technician'; you land on a page you can use (not an error). | H2: Not run
A3: cssd_technician:see:/dashboard | B3: Should see | C3: Core | D3: Open Dashboard | E3: Menu → Core → Dashboard (/dashboard) | F3: The screen opens with no 'access denied' or error message. Lists load; an empty list says so. Buttons to add or change things appear only where this role should do that. | G3: dashboard.view | H3: Not run
A4: cssd_technician:see:/approvals | B4: Should see | C4: Core | D4: Open Approvals | E4: Menu → Core → Approvals (/approvals) | F4: The screen opens with no 'access denied' or error message. Lists load; an empty list says so. Buttons to add or change things appear only where this role should do that. | H4: Not run
A5: cssd_technician:see:/health-pulse | B5: Should see | C5: Core | D5: Open Health Pulse | E5: Menu → Core → Health Pulse (/health-pulse) | F5: The screen opens with no 'access denied' or error message. Lists load; an empty list says so. Buttons to add or change things appear only where this role should do that. | G5: dashboard.view | H5: Not run
A6: cssd_technician:see:/cssd | B6: Should see | C6: Operations | D6: Open CSSD | E6: Menu → Operations → CSSD (/cssd) | F6: The screen opens with no 'access denied' or error message. Lists load; an empty list says so. Buttons to add or change things appear only where this role should do that. | G6: cssd.instruments.list | H6: Not run
A7: cssd_technician:menu | B7: Must not see | C7: Menu | D7: Menu shows only this role's screens | E7: Look through every menu group. | F7: These must NOT be in the menu: Token Board, Token Console, Patients, OPD Queue, Appointments, Telemedicine, Doctor Sign-offs, Emergency, Order Sets, Chronic Care, Home healthcare, Home visits, Lab, Radiology, Ward Stock, Pharmacy, Pharmacy Finance, Fulfilment Queue, Home Deliveries, Collection Counter, Blood Bank, IPD, Care View, Case sheet review, ICU, Nurse Activities, Operation Theatre, Diet & Kitchen, Bedside Portal, Billing, Insurance & TPA, Procurement, Indent & Store, Materials, Payroll, Front Office, Smart Scheduling, Command Center, Communications, Camp Management, Ambulance, Housekeeping, Facilities Management, Biomedical Engineering, Security, HR & Staffing, Learning (LMS), Medical Records, Clinical Knowledge, Directory, Hospital groups, Inter-hospital transfers, Inter-hospital stock, Marketing, Health packages, Testimonials, Micro-site settings, Quality, Infection Control, Consent Management, Regulatory Compliance, Analytics & Dashboards, Reports Center, Audit Trail, Utilization Review, Case Management, Ophthalmology, Dental, Cath Lab, Endoscopy, Psychiatry, Physical Medicine, Palliative Care, Maternity, Other Specialties, Clinical trials, Long-term care, Occupational Health, Users, Doctors, Roles & Permissions, Access Groups, Single Sign-On, Access Requests, NABH Indicators, Setup Center, Onboarding workbook, Settings, Document Templates, Built-in Pipelines, Forms, Test cycles, API keys, Webhooks, Doctor Schedules, Documents & Printing, Retrospective Entry, Device Integration, Paired Devices, Queues, Message Simulator. | H7: Not run
A8: cssd_technician:url:/admin/users | B8: Must not see | C8: Administration | D8: Typing the address of Users | E8: Type app.medbrains.in/admin/users into the address bar. | F8: You get an 'access denied' page or are sent back — none of that screen's data is shown, even briefly. | G8: admin.users.list | H8: Not run
A9: cssd_technician:url:/audit | B9: Must not see | C9: Compliance | D9: Typing the address of Audit Trail | E9: Type app.medbrains.in/audit into the address bar. | F9: You get an 'access denied' page or are sent back — none of that screen's data is shown, even briefly. | G9: audit.log.view | H9: Not run
A10: cssd_technician:url:/billing | B10: Must not see | C10: Finance | D10: Typing the address of Billing | E10: Type app.medbrains.in/billing into the address bar. | F10: You get an 'access denied' page or are sent back — none of that screen's data is shown, even briefly. | G10: billing.invoices.list | H10: Not run
A11: cssd_technician:url:/mrd | B11: Must not see | C11: Operations | D11: Typing the address of Medical Records | E11: Type app.medbrains.in/mrd into the address bar. | F11: You get an 'access denied' page or are sent back — none of that screen's data is shown, even briefly. | H11: Not run
A12: cssd_technician:wf:run-a-sterilisation-cycle | B12: Workflow | C12: CSSD | D12: Run a sterilisation cycle | E12: CSSD → receive a set → load into a cycle → record the indicator result → release. | F12: A failed indicator blocks release; released sets show as sterile with expiry. | H12: Not run

Sheet Blood Bank Technician
A1: Case | B1: Type | C1: Area | D1: What to test | E1: Steps | F1: Expected | G1: Permission | H1: Result | I1: Tester | J1: Date | K1: Notes
A2: blood_bank_tech:sign-in | B2: Sign in | C2: Sign in | D2: Sign in as Blood Bank Technician | E2: app.medbrains.in → hospital code AMH → username test_blood_bank_tech and the password from your test-accounts file. | F2: You are signed in; the header shows 'TEST - Blood Bank Technician'; you land on a page you can use (not an error). | H2: Not run
A3: blood_bank_tech:see:/dashboard | B3: Should see | C3: Core | D3: Open Dashboard | E3: Menu → Core → Dashboard (/dashboard) | F3: The screen opens with no 'access denied' or error message. Lists load; an empty list says so. Buttons to add or change things appear only where this role should do that. | G3: dashboard.view | H3: Not run
A4: blood_bank_tech:see:/approvals | B4: Should see | C4: Core | D4: Open Approvals | E4: Menu → Core → Approvals (/approvals) | F4: The screen opens with no 'access denied' or error message. Lists load; an empty list says so. Buttons to add or change things appear only where this role should do that. | H4: Not run
A5: blood_bank_tech:see:/health-pulse | B5: Should see | C5: Core | D5: Open Health Pulse | E5: Menu → Core → Health Pulse (/health-pulse) | F5: The screen opens with no 'access denied' or error message. Lists load; an empty list says so. Buttons to add or change things appear only where this role should do that. | G5: dashboard.view | H5: Not run
A6: blood_bank_tech:see:/blood-bank | B6: Should see | C6: Diagnostics | D6: Open Blood Bank | E6: Menu → Diagnostics → Blood Bank (/blood-bank) | F6: The screen opens with no 'access denied' or error message. Lists load; an empty list says so. Buttons to add or change things appear only where this role should do that. | G6: blood_bank.donors.list | H6: Not run
A7: blood_bank_tech:menu | B7: Must not see | C7: Menu | D7: Menu shows only this role's screens | E7: Look through every menu group. | F7: These must NOT be in the menu: Token Board, Token Console, Patients, OPD Queue, Appointments, Telemedicine, Doctor Sign-offs, Emergency, Order Sets, Chronic Care, Home healthcare, Home visits, Lab, Radiology, Ward Stock, Pharmacy, Pharmacy Finance, Fulfilment Queue, Home Deliveries, Collection Counter, IPD, Care View, Case sheet review, ICU, Nurse Activities, Operation Theatre, Diet & Kitchen, Bedside Portal, Billing, Insurance & TPA, Procurement, Indent & Store, Materials, Payroll, Front Office, Smart Scheduling, Command Center, Communications, Camp Management, Ambulance, Housekeeping, CSSD, Facilities Management, Biomedical Engineering, Security, HR & Staffing, Learning (LMS), Medical Records, Clinical Knowledge, Directory, Hospital groups, Inter-hospital transfers, Inter-hospital stock, Marketing, Health packages, Testimonials, Micro-site settings, Quality, Infection Control, Consent Management, Regulatory Compliance, Analytics & Dashboards, Reports Center, Audit Trail, Utilization Review, Case Management, Ophthalmology, Dental, Cath Lab, Endoscopy, Psychiatry, Physical Medicine, Palliative Care, Maternity, Other Specialties, Clinical trials, Long-term care, Occupational Health, Users, Doctors, Roles & Permissions, Access Groups, Single Sign-On, Access Requests, NABH Indicators, Setup Center, Onboarding workbook, Settings, Document Templates, Built-in Pipelines, Forms, Test cycles, API keys, Webhooks, Doctor Schedules, Documents & Printing, Retrospective Entry, Device Integration, Paired Devices, Queues, Message Simulator. | H7: Not run
A8: blood_bank_tech:url:/admin/users | B8: Must not see | C8: Administration | D8: Typing the address of Users | E8: Type app.medbrains.in/admin/users into the address bar. | F8: You get an 'access denied' page or are sent back — none of that screen's data is shown, even briefly. | G8: admin.users.list | H8: Not run
A9: blood_bank_tech:url:/audit | B9: Must not see | C9: Compliance | D9: Typing the address of Audit Trail | E9: Type app.medbrains.in/audit into the address bar. | F9: You get an 'access denied' page or are sent back — none of that screen's data is shown, even briefly. | G9: audit.log.view | H9: Not run
A10: blood_bank_tech:url:/billing | B10: Must not see | C10: Finance | D10: Typing the address of Billing | E10: Type app.medbrains.in/billing into the address bar. | F10: You get an 'access denied' page or are sent back — none of that screen's data is shown, even briefly. | G10: billing.invoices.list | H10: Not run
A11: blood_bank_tech:url:/mrd | B11: Must not see | C11: Operations | D11: Typing the address of Medical Records | E11: Type app.medbrains.in/mrd into the address bar. | F11: You get an 'access denied' page or are sent back — none of that screen's data is shown, even briefly. | H11: Not run
A12: blood_bank_tech:wf:issue-a-unit-after-crossmatch | B12: Workflow | C12: Blood Bank | D12: Issue a unit after crossmatch | E12: Blood Bank → a request → crossmatch a compatible unit → issue. | F12: Incompatible groups are refused; the issued unit leaves stock with the patient recorded. | H12: Not run

Sheet Marketing Executive
A1: Case | B1: Type | C1: Area | D1: What to test | E1: Steps | F1: Expected | G1: Permission | H1: Result | I1: Tester | J1: Date | K1: Notes
A2: marketing_executive:sign-in | B2: Sign in | C2: Sign in | D2: Sign in as Marketing Executive | E2: app.medbrains.in → hospital code AMH → username test_marketing_executive and the password from your test-accounts file. | F2: You are signed in; the header shows 'TEST - Marketing Executive'; you land on a page you can use (not an error). | H2: Not run
A3: marketing_executive:see:/dashboard | B3: Should see | C3: Core | D3: Open Dashboard | E3: Menu → Core → Dashboard (/dashboard) | F3: The screen opens with no 'access denied' or error message. Lists load; an empty list says so. Buttons to add or change things appear only where this role should do that. | G3: dashboard.view | H3: Not run
A4: marketing_executive:see:/approvals | B4: Should see | C4: Core | D4: Open Approvals | E4: Menu → Core → Approvals (/approvals) | F4: The screen opens with no 'access denied' or error message. Lists load; an empty list says so. Buttons to add or change things appear only where this role should do that. | H4: Not run
A5: marketing_executive:see:/health-pulse | B5: Should see | C5: Core | D5: Open Health Pulse | E5: Menu → Core → Health Pulse (/health-pulse) | F5: The screen opens with no 'access denied' or error message. Lists load; an empty list says so. Buttons to add or change things appear only where this role should do that. | G5: dashboard.view | H5: Not run
A6: marketing_executive:see:/marketing | B6: Should see | C6: Marketing & Web | D6: Open Marketing | E6: Menu → Marketing & Web → Marketing (/marketing) | F6: The screen opens with no 'access denied' or error message. Lists load; an empty list says so. Buttons to add or change things appear only where this role should do that. | G6: marketing.contacts.list | H6: Not run
A7: marketing_executive:see:/reports | B7: Should see | C7: Compliance | D7: Open Reports Center | E7: Menu → Compliance → Reports Center (/reports) | F7: The screen opens with no 'access denied' or error message. Lists load; an empty list says so. Buttons to add or change things appear only where this role should do that. | G7: analytics.view, billing.reports.view, quality.indicators.list… | H7: Not run
A8: marketing_executive:menu | B8: Must not see | C8: Menu | D8: Menu shows only this role's screens | E8: Look through every menu group. | F8: These must NOT be in the menu: Token Board, Token Console, Patients, OPD Queue, Appointments, Telemedicine, Doctor Sign-offs, Emergency, Order Sets, Chronic Care, Home healthcare, Home visits, Lab, Radiology, Ward Stock, Pharmacy, Pharmacy Finance, Fulfilment Queue, Home Deliveries, Collection Counter, Blood Bank, IPD, Care View, Case sheet review, ICU, Nurse Activities, Operation Theatre, Diet & Kitchen, Bedside Portal, Billing, Insurance & TPA, Procurement, Indent & Store, Materials, Payroll, Front Office, Smart Scheduling, Command Center, Communications, Camp Management, Ambulance, Housekeeping, CSSD, Facilities Management, Biomedical Engineering, Security, HR & Staffing, Learning (LMS), Medical Records, Clinical Knowledge, Directory, Hospital groups, Inter-hospital transfers, Inter-hospital stock, Health packages, Testimonials, Micro-site settings, Quality, Infection Control, Consent Management, Regulatory Compliance, Analytics & Dashboards, Audit Trail, Utilization Review, Case Management, Ophthalmology, Dental, Cath Lab, Endoscopy, Psychiatry, Physical Medicine, Palliative Care, Maternity, Other Specialties, Clinical trials, Long-term care, Occupational Health, Users, Doctors, Roles & Permissions, Access Groups, Single Sign-On, Access Requests, NABH Indicators, Setup Center, Onboarding workbook, Settings, Document Templates, Built-in Pipelines, Forms, Test cycles, API keys, Webhooks, Doctor Schedules, Documents & Printing, Retrospective Entry, Device Integration, Paired Devices, Queues, Message Simulator. | H8: Not run
A9: marketing_executive:url:/admin/users | B9: Must not see | C9: Administration | D9: Typing the address of Users | E9: Type app.medbrains.in/admin/users into the address bar. | F9: You get an 'access denied' page or are sent back — none of that screen's data is shown, even briefly. | G9: admin.users.list | H9: Not run
A10: marketing_executive:url:/audit | B10: Must not see | C10: Compliance | D10: Typing the address of Audit Trail | E10: Type app.medbrains.in/audit into the address bar. | F10: You get an 'access denied' page or are sent back — none of that screen's data is shown, even briefly. | G10: audit.log.view | H10: Not run
A11: marketing_executive:url:/billing | B11: Must not see | C11: Finance | D11: Typing the address of Billing | E11: Type app.medbrains.in/billing into the address bar. | F11: You get an 'access denied' page or are sent back — none of that screen's data is shown, even briefly. | G11: billing.invoices.list | H11: Not run
A12: marketing_executive:url:/mrd | B12: Must not see | C12: Operations | D12: Typing the address of Medical Records | E12: Type app.medbrains.in/mrd into the address bar. | F12: You get an 'access denied' page or are sent back — none of that screen's data is shown, even briefly. | H12: Not run
A13: marketing_executive:wf:create-a-campaign | B13: Workflow | C13: Marketing | D13: Create a campaign | E13: Marketing → new campaign. | F13: The campaign is listed; no patient clinical records are visible to marketing. | H13: Not run

Sheet Front Office Staff
A1: Case | B1: Type | C1: Area | D1: What to test | E1: Steps | F1: Expected | G1: Permission | H1: Result | I1: Tester | J1: Date | K1: Notes
A2: front_office_staff:sign-in | B2: Sign in | C2: Sign in | D2: Sign in as Front Office Staff | E2: app.medbrains.in → hospital code AMH → username test_front_office_staff and the password from your test-accounts file. | F2: You are signed in; the header shows 'TEST - Front Office Staff'; you land on a page you can use (not an error). | H2: Not run
A3: front_office_staff:see:/dashboard | B3: Should see | C3: Core | D3: Open Dashboard | E3: Menu → Core → Dashboard (/dashboard) | F3: The screen opens with no 'access denied' or error message. Lists load; an empty list says so. Buttons to add or change things appear only where this role should do that. | G3: dashboard.view | H3: Not run
A4: front_office_staff:see:/approvals | B4: Should see | C4: Core | D4: Open Approvals | E4: Menu → Core → Approvals (/approvals) | F4: The screen opens with no 'access denied' or error message. Lists load; an empty list says so. Buttons to add or change things appear only where this role should do that. | H4: Not run
A5: front_office_staff:see:/health-pulse | B5: Should see | C5: Core | D5: Open Health Pulse | E5: Menu → Core → Health Pulse (/health-pulse) | F5: The screen opens with no 'access denied' or error message. Lists load; an empty list says so. Buttons to add or change things appear only where this role should do that. | G5: dashboard.view | H5: Not run
A6: front_office_staff:see:/token-board | B6: Should see | C6: Core | D6: Open Token Board | E6: Menu → Core → Token Board (/token-board) | F6: The screen opens with no 'access denied' or error message. Lists load; an empty list says so. Buttons to add or change things appear only where this role should do that. | G6: front_office.queue.list | H6: Not run
A7: front_office_staff:see:/token-console | B7: Should see | C7: Core | D7: Open Token Console | E7: Menu → Core → Token Console (/token-console) | F7: The screen opens with no 'access denied' or error message. Lists load; an empty list says so. Buttons to add or change things appear only where this role should do that. | G7: front_office.queue.manage | H7: Not run
A8: front_office_staff:see:/front-office | B8: Should see | C8: Operations | D8: Open Front Office | E8: Menu → Operations → Front Office (/front-office) | F8: The screen opens with no 'access denied' or error message. Lists load; an empty list says so. Buttons to add or change things appear only where this role should do that. | G8: front_office.visitors.list, front_office.visitors.create, front_office.visitors.manage… | H8: Not run
A9: front_office_staff:see:/communications | B9: Should see | C9: Operations | D9: Open Communications | E9: Menu → Operations → Communications (/communications) | F9: The screen opens with no 'access denied' or error message. Lists load; an empty list says so. Buttons to add or change things appear only where this role should do that. | G9: communications.messages.list | H9: Not run
A10: front_office_staff:see:/marketing | B10: Should see | C10: Marketing & Web | D10: Open Marketing | E10: Menu → Marketing & Web → Marketing (/marketing) | F10: The screen opens with no 'access denied' or error message. Lists load; an empty list says so. Buttons to add or change things appear only where this role should do that. | G10: marketing.contacts.list | H10: Not run
A11: front_office_staff:see:/admin/queues | B11: Should see | C11: Administration | D11: Open Queues | E11: Menu → Administration → Admin → Queues (/admin/queues) | F11: The screen opens with no 'access denied' or error message. Lists load; an empty list says so. Buttons to add or change things appear only where this role should do that. | G11: front_office.queue.config.view | H11: Not run
A12: front_office_staff:menu | B12: Must not see | C12: Menu | D12: Menu shows only this role's screens | E12: Look through every menu group. | F12: These must NOT be in the menu: Patients, OPD Queue, Appointments, Telemedicine, Doctor Sign-offs, Emergency, Order Sets, Chronic Care, Home healthcare, Home visits, Lab, Radiology, Ward Stock, Pharmacy, Pharmacy Finance, Fulfilment Queue, Home Deliveries, Collection Counter, Blood Bank, IPD, Care View, Case sheet review, ICU, Nurse Activities, Operation Theatre, Diet & Kitchen, Bedside Portal, Billing, Insurance & TPA, Procurement, Indent & Store, Materials, Payroll, Smart Scheduling, Command Center, Camp Management, Ambulance, Housekeeping, CSSD, Facilities Management, Biomedical Engineering, Security, HR & Staffing, Learning (LMS), Medical Records, Clinical Knowledge, Directory, Hospital groups, Inter-hospital transfers, Inter-hospital stock, Health packages, Testimonials, Micro-site settings, Quality, Infection Control, Consent Management, Regulatory Compliance, Analytics & Dashboards, Reports Center, Audit Trail, Utilization Review, Case Management, Ophthalmology, Dental, Cath Lab, Endoscopy, Psychiatry, Physical Medicine, Palliative Care, Maternity, Other Specialties, Clinical trials, Long-term care, Occupational Health, Users, Doctors, Roles & Permissions, Access Groups, Single Sign-On, Access Requests, NABH Indicators, Setup Center, Onboarding workbook, Settings, Document Templates, Built-in Pipelines, Forms, Test cycles, API keys, Webhooks, Doctor Schedules, Documents & Printing, Retrospective Entry, Device Integration, Paired Devices, Message Simulator. | H12: Not run
A13: front_office_staff:url:/admin/users | B13: Must not see | C13: Administration | D13: Typing the address of Users | E13: Type app.medbrains.in/admin/users into the address bar. | F13: You get an 'access denied' page or are sent back — none of that screen's data is shown, even briefly. | G13: admin.users.list | H13: Not run
A14: front_office_staff:url:/audit | B14: Must not see | C14: Compliance | D14: Typing the address of Audit Trail | E14: Type app.medbrains.in/audit into the address bar. | F14: You get an 'access denied' page or are sent back — none of that screen's data is shown, even briefly. | G14: audit.log.view | H14: Not run
A15: front_office_staff:url:/billing | B15: Must not see | C15: Finance | D15: Typing the address of Billing | E15: Type app.medbrains.in/billing into the address bar. | F15: You get an 'access denied' page or are sent back — none of that screen's data is shown, even briefly. | G15: billing.invoices.list | H15: Not run
A16: front_office_staff:url:/mrd | B16: Must not see | C16: Operations | D16: Typing the address of Medical Records | E16: Type app.medbrains.in/mrd into the address bar. | F16: You get an 'access denied' page or are sent back — none of that screen's data is shown, even briefly. | H16: Not run
A17: front_office_staff:wf:call-the-next-patient | B17: Workflow | C17: Token Console | D17: Call the next patient | E17: Token Console → pick a counter → Call next. | F17: The next waiting token turns 'called'; the Token Board shows it. | H17: Not run
A18: front_office_staff:wf:visitor-enquiry-desk | B18: Workflow | C18: Front Office | D18: Visitor / enquiry desk | E18: Front Office → record a visitor or enquiry for an admitted patient. | F18: The entry is saved and listed with time and who recorded it. | H18: Not run

Sheet Infection Control Officer
A1: Case | B1: Type | C1: Area | D1: What to test | E1: Steps | F1: Expected | G1: Permission | H1: Result | I1: Tester | J1: Date | K1: Notes
A2: infection_control_officer:sign-in | B2: Sign in | C2: Sign in | D2: Sign in as Infection Control Officer | E2: app.medbrains.in → hospital code AMH → username test_infection_control_officer and the password from your test-accounts file. | F2: You are signed in; the header shows 'TEST - Infection Control Officer'; you land on a page you can use (not an error). | H2: Not run
A3: infection_control_officer:see:/dashboard | B3: Should see | C3: Core | D3: Open Dashboard | E3: Menu → Core → Dashboard (/dashboard) | F3: The screen opens with no 'access denied' or error message. Lists load; an empty list says so. Buttons to add or change things appear only where this role should do that. | G3: dashboard.view | H3: Not run
A4: infection_control_officer:see:/approvals | B4: Should see | C4: Core | D4: Open Approvals | E4: Menu → Core → Approvals (/approvals) | F4: The screen opens with no 'access denied' or error message. Lists load; an empty list says so. Buttons to add or change things appear only where this role should do that. | H4: Not run
A5: infection_control_officer:see:/health-pulse | B5: Should see | C5: Core | D5: Open Health Pulse | E5: Menu → Core → Health Pulse (/health-pulse) | F5: The screen opens with no 'access denied' or error message. Lists load; an empty list says so. Buttons to add or change things appear only where this role should do that. | G5: dashboard.view | H5: Not run
A6: infection_control_officer:see:/infection-control | B6: Should see | C6: Compliance | D6: Open Infection Control | E6: Menu → Compliance → Infection Control (/infection-control) | F6: The screen opens with no 'access denied' or error message. Lists load; an empty list says so. Buttons to add or change things appear only where this role should do that. | G6: infection_control.surveillance.list | H6: Not run
A7: infection_control_officer:menu | B7: Must not see | C7: Menu | D7: Menu shows only this role's screens | E7: Look through every menu group. | F7: These must NOT be in the menu: Token Board, Token Console, Patients, OPD Queue, Appointments, Telemedicine, Doctor Sign-offs, Emergency, Order Sets, Chronic Care, Home healthcare, Home visits, Lab, Radiology, Ward Stock, Pharmacy, Pharmacy Finance, Fulfilment Queue, Home Deliveries, Collection Counter, Blood Bank, IPD, Care View, Case sheet review, ICU, Nurse Activities, Operation Theatre, Diet & Kitchen, Bedside Portal, Billing, Insurance & TPA, Procurement, Indent & Store, Materials, Payroll, Front Office, Smart Scheduling, Command Center, Communications, Camp Management, Ambulance, Housekeeping, CSSD, Facilities Management, Biomedical Engineering, Security, HR & Staffing, Learning (LMS), Medical Records, Clinical Knowledge, Directory, Hospital groups, Inter-hospital transfers, Inter-hospital stock, Marketing, Health packages, Testimonials, Micro-site settings, Quality, Consent Management, Regulatory Compliance, Analytics & Dashboards, Reports Center, Audit Trail, Utilization Review, Case Management, Ophthalmology, Dental, Cath Lab, Endoscopy, Psychiatry, Physical Medicine, Palliative Care, Maternity, Other Specialties, Clinical trials, Long-term care, Occupational Health, Users, Doctors, Roles & Permissions, Access Groups, Single Sign-On, Access Requests, NABH Indicators, Setup Center, Onboarding workbook, Settings, Document Templates, Built-in Pipelines, Forms, Test cycles, API keys, Webhooks, Doctor Schedules, Documents & Printing, Retrospective Entry, Device Integration, Paired Devices, Queues, Message Simulator. | H7: Not run
A8: infection_control_officer:url:/admin/users | B8: Must not see | C8: Administration | D8: Typing the address of Users | E8: Type app.medbrains.in/admin/users into the address bar. | F8: You get an 'access denied' page or are sent back — none of that screen's data is shown, even briefly. | G8: admin.users.list | H8: Not run
A9: infection_control_officer:url:/audit | B9: Must not see | C9: Compliance | D9: Typing the address of Audit Trail | E9: Type app.medbrains.in/audit into the address bar. | F9: You get an 'access denied' page or are sent back — none of that screen's data is shown, even briefly. | G9: audit.log.view | H9: Not run
A10: infection_control_officer:url:/billing | B10: Must not see | C10: Finance | D10: Typing the address of Billing | E10: Type app.medbrains.in/billing into the address bar. | F10: You get an 'access denied' page or are sent back — none of that screen's data is shown, even briefly. | G10: billing.invoices.list | H10: Not run
A11: infection_control_officer:url:/mrd | B11: Must not see | C11: Operations | D11: Typing the address of Medical Records | E11: Type app.medbrains.in/mrd into the address bar. | F11: You get an 'access denied' page or are sent back — none of that screen's data is shown, even briefly. | H11: Not run
A12: infection_control_officer:wf:log-an-infection-event | B12: Workflow | C12: Infection Control | D12: Log an infection event | E12: Infection Control → record a hospital-acquired infection for a patient. | F12: It counts in the surveillance list and rates. | H12: Not run

Sheet Procurement Officer
A1: Case | B1: Type | C1: Area | D1: What to test | E1: Steps | F1: Expected | G1: Permission | H1: Result | I1: Tester | J1: Date | K1: Notes
A2: procurement_officer:sign-in | B2: Sign in | C2: Sign in | D2: Sign in as Procurement Officer | E2: app.medbrains.in → hospital code AMH → username test_procurement_officer and the password from your test-accounts file. | F2: You are signed in; the header shows 'TEST - Procurement Officer'; you land on a page you can use (not an error). | H2: Not run
A3: procurement_officer:see:/dashboard | B3: Should see | C3: Core | D3: Open Dashboard | E3: Menu → Core → Dashboard (/dashboard) | F3: The screen opens with no 'access denied' or error message. Lists load; an empty list says so. Buttons to add or change things appear only where this role should do that. | G3: dashboard.view | H3: Not run
A4: procurement_officer:see:/approvals | B4: Should see | C4: Core | D4: Open Approvals | E4: Menu → Core → Approvals (/approvals) | F4: The screen opens with no 'access denied' or error message. Lists load; an empty list says so. Buttons to add or change things appear only where this role should do that. | H4: Not run
A5: procurement_officer:see:/health-pulse | B5: Should see | C5: Core | D5: Open Health Pulse | E5: Menu → Core → Health Pulse (/health-pulse) | F5: The screen opens with no 'access denied' or error message. Lists load; an empty list says so. Buttons to add or change things appear only where this role should do that. | G5: dashboard.view | H5: Not run
A6: procurement_officer:see:/procurement | B6: Should see | C6: Finance | D6: Open Procurement | E6: Menu → Finance → Procurement (/procurement) | F6: The screen opens with no 'access denied' or error message. Lists load; an empty list says so. Buttons to add or change things appear only where this role should do that. | G6: procurement.vendors.list | H6: Not run
A7: procurement_officer:see:/materials | B7: Should see | C7: Finance | D7: Open Materials | E7: Menu → Finance → Materials (/materials) | F7: The screen opens with no 'access denied' or error message. Lists load; an empty list says so. Buttons to add or change things appear only where this role should do that. | G7: indent.list, assets.list, procurement.vendors.list… | H7: Not run
A8: procurement_officer:menu | B8: Must not see | C8: Menu | D8: Menu shows only this role's screens | E8: Look through every menu group. | F8: These must NOT be in the menu: Token Board, Token Console, Patients, OPD Queue, Appointments, Telemedicine, Doctor Sign-offs, Emergency, Order Sets, Chronic Care, Home healthcare, Home visits, Lab, Radiology, Ward Stock, Pharmacy, Pharmacy Finance, Fulfilment Queue, Home Deliveries, Collection Counter, Blood Bank, IPD, Care View, Case sheet review, ICU, Nurse Activities, Operation Theatre, Diet & Kitchen, Bedside Portal, Billing, Insurance & TPA, Indent & Store, Payroll, Front Office, Smart Scheduling, Command Center, Communications, Camp Management, Ambulance, Housekeeping, CSSD, Facilities Management, Biomedical Engineering, Security, HR & Staffing, Learning (LMS), Medical Records, Clinical Knowledge, Directory, Hospital groups, Inter-hospital transfers, Inter-hospital stock, Marketing, Health packages, Testimonials, Micro-site settings, Quality, Infection Control, Consent Management, Regulatory Compliance, Analytics & Dashboards, Reports Center, Audit Trail, Utilization Review, Case Management, Ophthalmology, Dental, Cath Lab, Endoscopy, Psychiatry, Physical Medicine, Palliative Care, Maternity, Other Specialties, Clinical trials, Long-term care, Occupational Health, Users, Doctors, Roles & Permissions, Access Groups, Single Sign-On, Access Requests, NABH Indicators, Setup Center, Onboarding workbook, Settings, Document Templates, Built-in Pipelines, Forms, Test cycles, API keys, Webhooks, Doctor Schedules, Documents & Printing, Retrospective Entry, Device Integration, Paired Devices, Queues, Message Simulator. | H8: Not run
A9: procurement_officer:url:/admin/users | B9: Must not see | C9: Administration | D9: Typing the address of Users | E9: Type app.medbrains.in/admin/users into the address bar. | F9: You get an 'access denied' page or are sent back — none of that screen's data is shown, even briefly. | G9: admin.users.list | H9: Not run
A10: procurement_officer:url:/audit | B10: Must not see | C10: Compliance | D10: Typing the address of Audit Trail | E10: Type app.medbrains.in/audit into the address bar. | F10: You get an 'access denied' page or are sent back — none of that screen's data is shown, even briefly. | G10: audit.log.view | H10: Not run
A11: procurement_officer:url:/billing | B11: Must not see | C11: Finance | D11: Typing the address of Billing | E11: Type app.medbrains.in/billing into the address bar. | F11: You get an 'access denied' page or are sent back — none of that screen's data is shown, even briefly. | G11: billing.invoices.list | H11: Not run
A12: procurement_officer:url:/mrd | B12: Must not see | C12: Operations | D12: Typing the address of Medical Records | E12: Type app.medbrains.in/mrd into the address bar. | F12: You get an 'access denied' page or are sent back — none of that screen's data is shown, even briefly. | H12: Not run
A13: procurement_officer:wf:purchase-order-to-goods-received | B13: Workflow | C13: Procurement | D13: Purchase order to goods received | E13: Procurement → raise a PO → (as test_store_keeper) receive the goods (GRN). | F13: Received quantities update stock; partial receipts keep the PO open. | H13: Not run

Sheet Store Keeper
A1: Case | B1: Type | C1: Area | D1: What to test | E1: Steps | F1: Expected | G1: Permission | H1: Result | I1: Tester | J1: Date | K1: Notes
A2: store_keeper:sign-in | B2: Sign in | C2: Sign in | D2: Sign in as Store Keeper | E2: app.medbrains.in → hospital code AMH → username test_store_keeper and the password from your test-accounts file. | F2: You are signed in; the header shows 'TEST - Store Keeper'; you land on a page you can use (not an error). | H2: Not run
A3: store_keeper:see:/dashboard | B3: Should see | C3: Core | D3: Open Dashboard | E3: Menu → Core → Dashboard (/dashboard) | F3: The screen opens with no 'access denied' or error message. Lists load; an empty list says so. Buttons to add or change things appear only where this role should do that. | G3: dashboard.view | H3: Not run
A4: store_keeper:see:/approvals | B4: Should see | C4: Core | D4: Open Approvals | E4: Menu → Core → Approvals (/approvals) | F4: The screen opens with no 'access denied' or error message. Lists load; an empty list says so. Buttons to add or change things appear only where this role should do that. | H4: Not run
A5: store_keeper:see:/health-pulse | B5: Should see | C5: Core | D5: Open Health Pulse | E5: Menu → Core → Health Pulse (/health-pulse) | F5: The screen opens with no 'access denied' or error message. Lists load; an empty list says so. Buttons to add or change things appear only where this role should do that. | G5: dashboard.view | H5: Not run
A6: store_keeper:see:/indent | B6: Should see | C6: Finance | D6: Open Indent & Store | E6: Menu → Finance → Indent & Store (/indent) | F6: The screen opens with no 'access denied' or error message. Lists load; an empty list says so. Buttons to add or change things appear only where this role should do that. | G6: indent.list | H6: Not run
A7: store_keeper:see:/materials | B7: Should see | C7: Finance | D7: Open Materials | E7: Menu → Finance → Materials (/materials) | F7: The screen opens with no 'access denied' or error message. Lists load; an empty list says so. Buttons to add or change things appear only where this role should do that. | G7: indent.list, assets.list, procurement.vendors.list… | H7: Not run
A8: store_keeper:menu | B8: Must not see | C8: Menu | D8: Menu shows only this role's screens | E8: Look through every menu group. | F8: These must NOT be in the menu: Token Board, Token Console, Patients, OPD Queue, Appointments, Telemedicine, Doctor Sign-offs, Emergency, Order Sets, Chronic Care, Home healthcare, Home visits, Lab, Radiology, Ward Stock, Pharmacy, Pharmacy Finance, Fulfilment Queue, Home Deliveries, Collection Counter, Blood Bank, IPD, Care View, Case sheet review, ICU, Nurse Activities, Operation Theatre, Diet & Kitchen, Bedside Portal, Billing, Insurance & TPA, Procurement, Payroll, Front Office, Smart Scheduling, Command Center, Communications, Camp Management, Ambulance, Housekeeping, CSSD, Facilities Management, Biomedical Engineering, Security, HR & Staffing, Learning (LMS), Medical Records, Clinical Knowledge, Directory, Hospital groups, Inter-hospital transfers, Inter-hospital stock, Marketing, Health packages, Testimonials, Micro-site settings, Quality, Infection Control, Consent Management, Regulatory Compliance, Analytics & Dashboards, Reports Center, Audit Trail, Utilization Review, Case Management, Ophthalmology, Dental, Cath Lab, Endoscopy, Psychiatry, Physical Medicine, Palliative Care, Maternity, Other Specialties, Clinical trials, Long-term care, Occupational Health, Users, Doctors, Roles & Permissions, Access Groups, Single Sign-On, Access Requests, NABH Indicators, Setup Center, Onboarding workbook, Settings, Document Templates, Built-in Pipelines, Forms, Test cycles, API keys, Webhooks, Doctor Schedules, Documents & Printing, Retrospective Entry, Device Integration, Paired Devices, Queues, Message Simulator. | H8: Not run
A9: store_keeper:url:/admin/users | B9: Must not see | C9: Administration | D9: Typing the address of Users | E9: Type app.medbrains.in/admin/users into the address bar. | F9: You get an 'access denied' page or are sent back — none of that screen's data is shown, even briefly. | G9: admin.users.list | H9: Not run
A10: store_keeper:url:/audit | B10: Must not see | C10: Compliance | D10: Typing the address of Audit Trail | E10: Type app.medbrains.in/audit into the address bar. | F10: You get an 'access denied' page or are sent back — none of that screen's data is shown, even briefly. | G10: audit.log.view | H10: Not run
A11: store_keeper:url:/billing | B11: Must not see | C11: Finance | D11: Typing the address of Billing | E11: Type app.medbrains.in/billing into the address bar. | F11: You get an 'access denied' page or are sent back — none of that screen's data is shown, even briefly. | G11: billing.invoices.list | H11: Not run
A12: store_keeper:url:/mrd | B12: Must not see | C12: Operations | D12: Typing the address of Medical Records | E12: Type app.medbrains.in/mrd into the address bar. | F12: You get an 'access denied' page or are sent back — none of that screen's data is shown, even briefly. | H12: Not run
A13: store_keeper:wf:issue-against-an-indent | B13: Workflow | C13: Indent & Store | D13: Issue against an indent | E13: Indent & Store → a ward's indent → issue items. | F13: Store stock reduces; the ward's stock increases. | H13: Not run

Sheet HR Officer
A1: Case | B1: Type | C1: Area | D1: What to test | E1: Steps | F1: Expected | G1: Permission | H1: Result | I1: Tester | J1: Date | K1: Notes
A2: hr_officer:sign-in | B2: Sign in | C2: Sign in | D2: Sign in as HR Officer | E2: app.medbrains.in → hospital code AMH → username test_hr_officer and the password from your test-accounts file. | F2: You are signed in; the header shows 'TEST - HR Officer'; you land on a page you can use (not an error). | H2: Not run
A3: hr_officer:see:/dashboard | B3: Should see | C3: Core | D3: Open Dashboard | E3: Menu → Core → Dashboard (/dashboard) | F3: The screen opens with no 'access denied' or error message. Lists load; an empty list says so. Buttons to add or change things appear only where this role should do that. | G3: dashboard.view | H3: Not run
A4: hr_officer:see:/approvals | B4: Should see | C4: Core | D4: Open Approvals | E4: Menu → Core → Approvals (/approvals) | F4: The screen opens with no 'access denied' or error message. Lists load; an empty list says so. Buttons to add or change things appear only where this role should do that. | H4: Not run
A5: hr_officer:see:/health-pulse | B5: Should see | C5: Core | D5: Open Health Pulse | E5: Menu → Core → Health Pulse (/health-pulse) | F5: The screen opens with no 'access denied' or error message. Lists load; an empty list says so. Buttons to add or change things appear only where this role should do that. | G5: dashboard.view | H5: Not run
A6: hr_officer:see:/hr/payroll | B6: Should see | C6: Finance | D6: Open Payroll | E6: Menu → Finance → Payroll (/hr/payroll) | F6: The screen opens with no 'access denied' or error message. Lists load; an empty list says so. Buttons to add or change things appear only where this role should do that. | G6: hr.payroll.structures.list | H6: Not run
A7: hr_officer:see:/hr | B7: Should see | C7: Operations | D7: Open HR & Staffing | E7: Menu → Operations → HR & Staffing (/hr) | F7: The screen opens with no 'access denied' or error message. Lists load; an empty list says so. Buttons to add or change things appear only where this role should do that. | G7: hr.employees.list | H7: Not run
